{
"meta":{"test_sets":[],"test_metrics":[],"learn_metrics":[{"best_value":"Min","name":"Logloss"}],"launch_mode":"Train","parameters":"","iteration_count":1000,"learn_sets":["learn"],"name":"experiment"},
"iterations":[
{"learn":[0.649289856],"iteration":0,"passed_time":0.04069306971,"remaining_time":40.65237664},
{"learn":[0.610617747],"iteration":1,"passed_time":0.07791200369,"remaining_time":38.87808984},
{"learn":[0.5755797348],"iteration":2,"passed_time":0.1329868014,"remaining_time":44.19594701},
{"learn":[0.5446618525],"iteration":3,"passed_time":0.1727967861,"remaining_time":43.02639973},
{"learn":[0.5159491552],"iteration":4,"passed_time":0.2106846878,"remaining_time":41.92625288},
{"learn":[0.4904579468],"iteration":5,"passed_time":0.2511608257,"remaining_time":41.60897679},
{"learn":[0.4678771261],"iteration":6,"passed_time":0.2933976494,"remaining_time":41.62055226},
{"learn":[0.4475123749],"iteration":7,"passed_time":0.3337775937,"remaining_time":41.38842161},
{"learn":[0.4286945114],"iteration":8,"passed_time":0.3721032682,"remaining_time":40.97270431},
{"learn":[0.4123594437],"iteration":9,"passed_time":0.4118430871,"remaining_time":40.77246562},
{"learn":[0.3975002009],"iteration":10,"passed_time":0.4512581428,"remaining_time":40.57220939},
{"learn":[0.3836390279],"iteration":11,"passed_time":0.4914469271,"remaining_time":40.46246366},
{"learn":[0.3716821899],"iteration":12,"passed_time":0.5307841023,"remaining_time":40.29876223},
{"learn":[0.3606553879],"iteration":13,"passed_time":0.5737690766,"remaining_time":40.40973639},
{"learn":[0.3507371953],"iteration":14,"passed_time":0.6139630144,"remaining_time":40.31690461},
{"learn":[0.3413049952],"iteration":15,"passed_time":0.6528403094,"remaining_time":40.14967903},
{"learn":[0.3333551178],"iteration":16,"passed_time":0.6916780785,"remaining_time":39.99526772},
{"learn":[0.325431469],"iteration":17,"passed_time":0.7305258665,"remaining_time":39.8542445},
{"learn":[0.3189449425],"iteration":18,"passed_time":0.7701105174,"remaining_time":39.76202198},
{"learn":[0.3127675921],"iteration":19,"passed_time":0.8140976845,"remaining_time":39.89078654},
{"learn":[0.3071874835],"iteration":20,"passed_time":0.8546269864,"remaining_time":39.84189618},
{"learn":[0.3021954549],"iteration":21,"passed_time":0.8940674792,"remaining_time":39.7453634},
{"learn":[0.2973338127],"iteration":22,"passed_time":0.9338741755,"remaining_time":39.66935085},
{"learn":[0.293196242],"iteration":23,"passed_time":0.9726904148,"remaining_time":39.55607687},
{"learn":[0.2893130989],"iteration":24,"passed_time":1.016724041,"remaining_time":39.6522376},
{"learn":[0.2852368927],"iteration":25,"passed_time":1.058617647,"remaining_time":39.65744569},
{"learn":[0.2818964945],"iteration":26,"passed_time":1.098207666,"remaining_time":39.57615032},
{"learn":[0.2787351519],"iteration":27,"passed_time":1.138169372,"remaining_time":39.51073677},
{"learn":[0.2759392675],"iteration":28,"passed_time":1.177150505,"remaining_time":39.41424623},
{"learn":[0.2735059942],"iteration":29,"passed_time":1.216849306,"remaining_time":39.34479421},
{"learn":[0.271366492],"iteration":30,"passed_time":1.258907505,"remaining_time":39.35101201},
{"learn":[0.2692661196],"iteration":31,"passed_time":1.302201722,"remaining_time":39.39160208},
{"learn":[0.267054395],"iteration":32,"passed_time":1.342433143,"remaining_time":39.33735908},
{"learn":[0.2651490733],"iteration":33,"passed_time":1.381726575,"remaining_time":39.25729034},
{"learn":[0.2637380498],"iteration":34,"passed_time":1.420398914,"remaining_time":39.16242719},
{"learn":[0.2619564934],"iteration":35,"passed_time":1.459131522,"remaining_time":39.07229964},
{"learn":[0.2605497119],"iteration":36,"passed_time":1.500278059,"remaining_time":39.04777758},
{"learn":[0.2592063192],"iteration":37,"passed_time":1.543202038,"remaining_time":39.06737791},
{"learn":[0.2576573283],"iteration":38,"passed_time":1.584345404,"remaining_time":39.03989573},
{"learn":[0.2562822444],"iteration":39,"passed_time":1.625161177,"remaining_time":39.00386824},
{"learn":[0.2551583875],"iteration":40,"passed_time":1.666932538,"remaining_time":38.98995862},
{"learn":[0.2538248685],"iteration":41,"passed_time":1.706025624,"remaining_time":38.9136321},
{"learn":[0.2527174288],"iteration":42,"passed_time":1.750790434,"remaining_time":38.96526618},
{"learn":[0.2515167402],"iteration":43,"passed_time":1.792898802,"remaining_time":38.95480124},
{"learn":[0.2507230301],"iteration":44,"passed_time":1.832260803,"remaining_time":38.88464593},
{"learn":[0.2497399839],"iteration":45,"passed_time":1.87228022,"remaining_time":38.82946369},
{"learn":[0.2487528572],"iteration":46,"passed_time":1.911721114,"remaining_time":38.76319621},
{"learn":[0.2478272298],"iteration":47,"passed_time":1.951911613,"remaining_time":38.71291366},
{"learn":[0.2471267026],"iteration":48,"passed_time":1.994491426,"remaining_time":38.70941523},
{"learn":[0.2462038193],"iteration":49,"passed_time":2.038612184,"remaining_time":38.7336315},
{"learn":[0.2456031914],"iteration":50,"passed_time":2.080829119,"remaining_time":38.71974183},
{"learn":[0.2448039462],"iteration":51,"passed_time":2.121375559,"remaining_time":38.67430827},
{"learn":[0.2441114044],"iteration":52,"passed_time":2.162250925,"remaining_time":38.63493634},
{"learn":[0.2434886983],"iteration":53,"passed_time":2.20461314,"remaining_time":38.62155613},
{"learn":[0.2428754018],"iteration":54,"passed_time":2.245605333,"remaining_time":38.58358254},
{"learn":[0.2423251559],"iteration":55,"passed_time":2.289761587,"remaining_time":38.59883819},
{"learn":[0.2417556585],"iteration":56,"passed_time":2.329696507,"remaining_time":38.54217204},
{"learn":[0.2413351517],"iteration":57,"passed_time":2.367604983,"remaining_time":38.45317059},
{"learn":[0.2406076113],"iteration":58,"passed_time":2.408647716,"remaining_time":38.41588985},
{"learn":[0.2400023664],"iteration":59,"passed_time":2.45175841,"remaining_time":38.41088175},
{"learn":[0.239453186],"iteration":60,"passed_time":2.497104905,"remaining_time":38.43904108},
{"learn":[0.2388489342],"iteration":61,"passed_time":2.538489242,"remaining_time":38.40488562},
{"learn":[0.2382811445],"iteration":62,"passed_time":2.579189843,"remaining_time":38.36033148},
{"learn":[0.2378038775],"iteration":63,"passed_time":2.620132534,"remaining_time":38.31943831},
{"learn":[0.2374177221],"iteration":64,"passed_time":2.660420551,"remaining_time":38.26912639},
{"learn":[0.2368748309],"iteration":65,"passed_time":2.705702977,"remaining_time":38.28979667},
{"learn":[0.2363151449],"iteration":66,"passed_time":2.750193846,"remaining_time":38.2974755},
{"learn":[0.2356794217],"iteration":67,"passed_time":2.790488215,"remaining_time":38.24610318},
{"learn":[0.2353551928],"iteration":68,"passed_time":2.830276108,"remaining_time":38.18821821},
{"learn":[0.234979201],"iteration":69,"passed_time":2.871618823,"remaining_time":38.15150722},
{"learn":[0.2345433668],"iteration":70,"passed_time":2.911205762,"remaining_time":38.0916923},
{"learn":[0.2342546107],"iteration":71,"passed_time":2.956655466,"remaining_time":38.10800378},
{"learn":[0.233913353],"iteration":72,"passed_time":2.998251445,"remaining_time":38.07368616},
{"learn":[0.2335485535],"iteration":73,"passed_time":3.037395501,"remaining_time":38.00848965},
{"learn":[0.2330855204],"iteration":74,"passed_time":3.078906079,"remaining_time":37.97317497},
{"learn":[0.2328290291],"iteration":75,"passed_time":3.117156185,"remaining_time":37.89805677},
{"learn":[0.2325749779],"iteration":76,"passed_time":3.156611542,"remaining_time":37.83834355},
{"learn":[0.2321317724],"iteration":77,"passed_time":3.198115275,"remaining_time":37.80336261},
{"learn":[0.2317886505],"iteration":78,"passed_time":3.239946891,"remaining_time":37.77203907},
{"learn":[0.2313291842],"iteration":79,"passed_time":3.282504238,"remaining_time":37.74879874},
{"learn":[0.2309295858],"iteration":80,"passed_time":3.322278516,"remaining_time":37.69350563},
{"learn":[0.2306413104],"iteration":81,"passed_time":3.361651979,"remaining_time":37.63410386},
{"learn":[0.2302188212],"iteration":82,"passed_time":3.402266801,"remaining_time":37.58889948},
{"learn":[0.2299071897],"iteration":83,"passed_time":3.445297135,"remaining_time":37.57014494},
{"learn":[0.2296886749],"iteration":84,"passed_time":3.485536743,"remaining_time":37.52077788},
{"learn":[0.2293747813],"iteration":85,"passed_time":3.528105211,"remaining_time":37.49637399},
{"learn":[0.2290486883],"iteration":86,"passed_time":3.566864344,"remaining_time":37.4315764},
{"learn":[0.2287380765],"iteration":87,"passed_time":3.607660761,"remaining_time":37.38848425},
{"learn":[0.2283244667],"iteration":88,"passed_time":3.649798515,"remaining_time":37.35917356},
{"learn":[0.2280750326],"iteration":89,"passed_time":3.691058793,"remaining_time":37.32070557},
{"learn":[0.2278832397],"iteration":90,"passed_time":3.730794746,"remaining_time":37.26694972},
{"learn":[0.2274861285],"iteration":91,"passed_time":3.769715631,"remaining_time":37.20545427},
{"learn":[0.2270664622],"iteration":92,"passed_time":3.812988889,"remaining_time":37.18689163},
{"learn":[0.2267679596],"iteration":93,"passed_time":3.854638266,"remaining_time":37.1521518},
{"learn":[0.2264894168],"iteration":94,"passed_time":3.896393182,"remaining_time":37.11827189},
{"learn":[0.226184564],"iteration":95,"passed_time":3.938939592,"remaining_time":37.09168116},
{"learn":[0.2259356677],"iteration":96,"passed_time":3.978923113,"remaining_time":37.0409028},
{"learn":[0.2256519623],"iteration":97,"passed_time":4.019261983,"remaining_time":36.9936154},
{"learn":[0.2253349368],"iteration":98,"passed_time":4.062150297,"remaining_time":36.96967089},
{"learn":[0.2253113263],"iteration":99,"passed_time":4.101706259,"remaining_time":36.91535633},
{"learn":[0.2251734047],"iteration":100,"passed_time":4.142470844,"remaining_time":36.87209196},
{"learn":[0.2248989182],"iteration":101,"passed_time":4.182593398,"remaining_time":36.82322423},
{"learn":[0.2247307625],"iteration":102,"passed_time":4.222692109,"remaining_time":36.77431866},
{"learn":[0.2244070155],"iteration":103,"passed_time":4.26657502,"remaining_time":36.75818479},
{"learn":[0.2241039238],"iteration":104,"passed_time":4.30821134,"remaining_time":36.72237285},
{"learn":[0.2237691867],"iteration":105,"passed_time":4.349523612,"remaining_time":36.68371801},
{"learn":[0.2234567922],"iteration":106,"passed_time":4.389210055,"remaining_time":36.63144467},
{"learn":[0.2233026314],"iteration":107,"passed_time":4.427547276,"remaining_time":36.56826084},
{"learn":[0.2231604309],"iteration":108,"passed_time":4.468558911,"remaining_time":36.5273944},
{"learn":[0.2229837227],"iteration":109,"passed_time":4.510880812,"remaining_time":36.49712657},
{"learn":[0.222791907],"iteration":110,"passed_time":4.550615621,"remaining_time":36.4459215},
{"learn":[0.2225264359],"iteration":111,"passed_time":4.590169862,"remaining_time":36.39348962},
{"learn":[0.2223152593],"iteration":112,"passed_time":4.628018845,"remaining_time":36.32790013},
{"learn":[0.2220391426],"iteration":113,"passed_time":4.667376097,"remaining_time":36.27451949},
{"learn":[0.2219216614],"iteration":114,"passed_time":4.707007632,"remaining_time":36.22349351},
{"learn":[0.2215993563],"iteration":115,"passed_time":4.749497833,"remaining_time":36.194449},
{"learn":[0.2213764877],"iteration":116,"passed_time":4.790142156,"remaining_time":36.15124379},
{"learn":[0.2211789563],"iteration":117,"passed_time":4.828446189,"remaining_time":36.09058931},
{"learn":[0.2209189631],"iteration":118,"passed_time":4.869439404,"remaining_time":36.05021945},
{"learn":[0.2206270536],"iteration":119,"passed_time":4.907606739,"remaining_time":35.98911609},
{"learn":[0.2206115608],"iteration":120,"passed_time":4.947024366,"remaining_time":35.93747453},
{"learn":[0.2205876617],"iteration":121,"passed_time":4.984710652,"remaining_time":35.87357338},
{"learn":[0.2204309476],"iteration":122,"passed_time":5.023812404,"remaining_time":35.82019088},
{"learn":[0.2203253771],"iteration":123,"passed_time":5.062624049,"remaining_time":35.76498925},
{"learn":[0.220141449],"iteration":124,"passed_time":5.100239393,"remaining_time":35.70167575},
{"learn":[0.2199693883],"iteration":125,"passed_time":5.140462759,"remaining_time":35.65686073},
{"learn":[0.2196648585],"iteration":126,"passed_time":5.179377465,"remaining_time":35.60312226},
{"learn":[0.219641393],"iteration":127,"passed_time":5.218572831,"remaining_time":35.55152741},
{"learn":[0.2195333417],"iteration":128,"passed_time":5.256472434,"remaining_time":35.49137589},
{"learn":[0.2194629491],"iteration":129,"passed_time":5.296034199,"remaining_time":35.44269041},
{"learn":[0.2191697973],"iteration":130,"passed_time":5.336456302,"remaining_time":35.39985135},
{"learn":[0.2189617538],"iteration":131,"passed_time":5.375298261,"remaining_time":35.34665826},
{"learn":[0.2187035128],"iteration":132,"passed_time":5.415211,"remaining_time":35.30066118},
{"learn":[0.2184607086],"iteration":133,"passed_time":5.458267062,"remaining_time":35.27506922},
{"learn":[0.2182718163],"iteration":134,"passed_time":5.496262967,"remaining_time":35.21679605},
{"learn":[0.2182557704],"iteration":135,"passed_time":5.537437141,"remaining_time":35.17901242},
{"learn":[0.2180679309],"iteration":136,"passed_time":5.576759698,"remaining_time":35.12951547},
{"learn":[0.2180388769],"iteration":137,"passed_time":5.616309199,"remaining_time":35.08158355},
{"learn":[0.2180158526],"iteration":138,"passed_time":5.65671949,"remaining_time":35.03910418},
{"learn":[0.2179626579],"iteration":139,"passed_time":5.696665611,"remaining_time":34.99380304},
{"learn":[0.2179088771],"iteration":140,"passed_time":5.735494306,"remaining_time":34.94177028},
{"learn":[0.2177723045],"iteration":141,"passed_time":5.774097058,"remaining_time":34.88855828},
{"learn":[0.2177466304],"iteration":142,"passed_time":5.814355861,"remaining_time":34.84547533},
{"learn":[0.2176252925],"iteration":143,"passed_time":5.85351242,"remaining_time":34.79587939},
{"learn":[0.2175486844],"iteration":144,"passed_time":5.906518312,"remaining_time":34.82809074},
{"learn":[0.2173870087],"iteration":145,"passed_time":5.949026082,"remaining_time":34.7977279},
{"learn":[0.2173176409],"iteration":146,"passed_time":5.98710541,"remaining_time":34.74150282},
{"learn":[0.2171262678],"iteration":147,"passed_time":6.026475648,"remaining_time":34.69295441},
{"learn":[0.2169498304],"iteration":148,"passed_time":6.066972788,"remaining_time":34.65096539},
{"learn":[0.2167982877],"iteration":149,"passed_time":6.105701637,"remaining_time":34.59897594},
{"learn":[0.2166231537],"iteration":150,"passed_time":6.148839091,"remaining_time":34.57194959},
{"learn":[0.21637662],"iteration":151,"passed_time":6.191288543,"remaining_time":34.54087292},
{"learn":[0.2162075195],"iteration":152,"passed_time":6.230146922,"remaining_time":34.4897676},
{"learn":[0.216137291],"iteration":153,"passed_time":6.269840348,"remaining_time":34.44340867},
{"learn":[0.2159964587],"iteration":154,"passed_time":6.311565401,"remaining_time":34.40821138},
{"learn":[0.2159348043],"iteration":155,"passed_time":6.351388219,"remaining_time":34.36263882},
{"learn":[0.2158039869],"iteration":156,"passed_time":6.396382953,"remaining_time":34.34490974},
{"learn":[0.2157321981],"iteration":157,"passed_time":6.436661408,"remaining_time":34.30170193},
{"learn":[0.2156816177],"iteration":158,"passed_time":6.475511293,"remaining_time":34.25097482},
{"learn":[0.2155686582],"iteration":159,"passed_time":6.517926851,"remaining_time":34.21911597},
{"learn":[0.2155503515],"iteration":160,"passed_time":6.556120905,"remaining_time":34.16512695},
{"learn":[0.2154484418],"iteration":161,"passed_time":6.599642754,"remaining_time":34.13889277},
{"learn":[0.2152869733],"iteration":162,"passed_time":6.640490726,"remaining_time":34.09871618},
{"learn":[0.215104318],"iteration":163,"passed_time":6.680767067,"remaining_time":34.05561749},
{"learn":[0.2150350863],"iteration":164,"passed_time":6.72054507,"remaining_time":34.01003111},
{"learn":[0.2150204608],"iteration":165,"passed_time":6.75819708,"remaining_time":33.95383352},
{"learn":[0.2148172862],"iteration":166,"passed_time":6.803350007,"remaining_time":33.93527279},
{"learn":[0.2145614522],"iteration":167,"passed_time":6.84927999,"remaining_time":33.92024376},
{"learn":[0.2143755569],"iteration":168,"passed_time":6.889205597,"remaining_time":33.87532456},
{"learn":[0.2143481979],"iteration":169,"passed_time":6.927909132,"remaining_time":33.82449753},
{"learn":[0.2142360954],"iteration":170,"passed_time":6.965967992,"remaining_time":33.77068693},
{"learn":[0.214044988],"iteration":171,"passed_time":7.006528197,"remaining_time":33.72910085},
{"learn":[0.2138635902],"iteration":172,"passed_time":7.052827163,"remaining_time":33.7149599},
{"learn":[0.2137491061],"iteration":173,"passed_time":7.094241966,"remaining_time":33.67726359},
{"learn":[0.2136550496],"iteration":174,"passed_time":7.134337584,"remaining_time":33.63330575},
{"learn":[0.2135545769],"iteration":175,"passed_time":7.17292973,"remaining_time":33.58235283},
{"learn":[0.2135347786],"iteration":176,"passed_time":7.210468465,"remaining_time":33.52664151},
{"learn":[0.2134974887],"iteration":177,"passed_time":7.248654159,"remaining_time":33.47412201},
{"learn":[0.2133220113],"iteration":178,"passed_time":7.291335156,"remaining_time":33.4423808},
{"learn":[0.2132893702],"iteration":179,"passed_time":7.333605221,"remaining_time":33.40864601},
{"learn":[0.2132695605],"iteration":180,"passed_time":7.373925094,"remaining_time":33.36599255},
{"learn":[0.213094134],"iteration":181,"passed_time":7.41709883,"remaining_time":33.33619144},
{"learn":[0.2130763664],"iteration":182,"passed_time":7.457675937,"remaining_time":33.29465159},
{"learn":[0.2130596034],"iteration":183,"passed_time":7.49495243,"remaining_time":33.23848469},
{"learn":[0.2130366414],"iteration":184,"passed_time":7.53780412,"remaining_time":33.20708301},
{"learn":[0.2129987475],"iteration":185,"passed_time":7.579444779,"remaining_time":33.17025833},
{"learn":[0.2129769847],"iteration":186,"passed_time":7.616571341,"remaining_time":33.11375668},
{"learn":[0.2128681056],"iteration":187,"passed_time":7.655980696,"remaining_time":33.06732088},
{"learn":[0.2128370158],"iteration":188,"passed_time":7.693353497,"remaining_time":33.01222056},
{"learn":[0.2128142014],"iteration":189,"passed_time":7.7347345,"remaining_time":32.97439445},
{"learn":[0.2127859586],"iteration":190,"passed_time":7.775367736,"remaining_time":32.93336387},
{"learn":[0.2127624003],"iteration":191,"passed_time":7.8146642,"remaining_time":32.88671184},
{"learn":[0.2125630048],"iteration":192,"passed_time":7.855865245,"remaining_time":32.84809976},
{"learn":[0.2123860944],"iteration":193,"passed_time":7.895279788,"remaining_time":32.80203871},
{"learn":[0.2122404531],"iteration":194,"passed_time":7.935725733,"remaining_time":32.76030367},
{"learn":[0.2120811297],"iteration":195,"passed_time":7.976002376,"remaining_time":32.7178873},
{"learn":[0.2118731168],"iteration":196,"passed_time":8.018042374,"remaining_time":32.68268034},
{"learn":[0.2117837499],"iteration":197,"passed_time":8.058490966,"remaining_time":32.64095836},
{"learn":[0.2115844574],"iteration":198,"passed_time":8.096749474,"remaining_time":32.59043381},
{"learn":[0.2114493103],"iteration":199,"passed_time":8.135517813,"remaining_time":32.54207125},
{"learn":[0.2113673426],"iteration":200,"passed_time":8.172705041,"remaining_time":32.48751905},
{"learn":[0.2113229446],"iteration":201,"passed_time":8.212413765,"remaining_time":32.44309992},
{"learn":[0.2111934992],"iteration":202,"passed_time":8.256308016,"remaining_time":32.41516004},
{"learn":[0.2111716334],"iteration":203,"passed_time":8.296366539,"remaining_time":32.37209689},
{"learn":[0.2111509844],"iteration":204,"passed_time":8.334739621,"remaining_time":32.32252682},
{"learn":[0.2111348979],"iteration":205,"passed_time":8.372386384,"remaining_time":32.27026597},
{"learn":[0.2108607915],"iteration":206,"passed_time":8.413962103,"remaining_time":32.23319781},
{"learn":[0.2107922757],"iteration":207,"passed_time":8.457526135,"remaining_time":32.20365721},
{"learn":[0.2106872164],"iteration":208,"passed_time":8.497997296,"remaining_time":32.16227685},
{"learn":[0.210667113],"iteration":209,"passed_time":8.538175973,"remaining_time":32.11980485},
{"learn":[0.2105218925],"iteration":210,"passed_time":8.577232631,"remaining_time":32.07315899},
{"learn":[0.2104369761],"iteration":211,"passed_time":8.614309594,"remaining_time":32.01922623},
{"learn":[0.2103875987],"iteration":212,"passed_time":8.653127672,"remaining_time":31.97188487},
{"learn":[0.2103610878],"iteration":213,"passed_time":8.691847868,"remaining_time":31.92426366},
{"learn":[0.2101982803],"iteration":214,"passed_time":8.734937426,"remaining_time":31.89267851},
{"learn":[0.210180926],"iteration":215,"passed_time":8.775173534,"remaining_time":31.85062986},
{"learn":[0.2099393667],"iteration":216,"passed_time":8.816052409,"remaining_time":31.81091722},
{"learn":[0.2098583934],"iteration":217,"passed_time":8.857232497,"remaining_time":31.77227437},
{"learn":[0.2097606646],"iteration":218,"passed_time":8.895799382,"remaining_time":31.72428912},
{"learn":[0.2097403526],"iteration":219,"passed_time":8.936663671,"remaining_time":31.68453484},
{"learn":[0.2096941363],"iteration":220,"passed_time":8.977335244,"remaining_time":31.6440912},
{"learn":[0.2094776815],"iteration":221,"passed_time":9.01651324,"remaining_time":31.59841126},
{"learn":[0.209430481],"iteration":222,"passed_time":9.056585259,"remaining_time":31.55590469},
{"learn":[0.2092655538],"iteration":223,"passed_time":9.095472783,"remaining_time":31.50931643},
{"learn":[0.20923526],"iteration":224,"passed_time":9.132979869,"remaining_time":31.45804177},
{"learn":[0.2091736488],"iteration":225,"passed_time":9.174603861,"remaining_time":31.42098844},
{"learn":[0.2089879239],"iteration":226,"passed_time":9.215939139,"remaining_time":31.38291169},
{"learn":[0.2089669418],"iteration":227,"passed_time":9.256954169,"remaining_time":31.34372201},
{"learn":[0.2088664653],"iteration":228,"passed_time":9.297539827,"remaining_time":31.30307077},
{"learn":[0.2088396695],"iteration":229,"passed_time":9.334590418,"remaining_time":31.25058531},
{"learn":[0.2087691243],"iteration":230,"passed_time":9.373102375,"remaining_time":31.20309838},
{"learn":[0.2087386208],"iteration":231,"passed_time":9.41390527,"remaining_time":31.16327262},
{"learn":[0.2087048162],"iteration":232,"passed_time":9.455241174,"remaining_time":31.12519305},
{"learn":[0.2086803729],"iteration":233,"passed_time":9.492889126,"remaining_time":31.07501312},
{"learn":[0.2086510709],"iteration":234,"passed_time":9.530754439,"remaining_time":31.02564743},
{"learn":[0.2086248868],"iteration":235,"passed_time":9.569458602,"remaining_time":30.9790948},
{"learn":[0.2086015155],"iteration":236,"passed_time":9.6066264,"remaining_time":30.92766221},
{"learn":[0.2084168104],"iteration":237,"passed_time":9.64778326,"remaining_time":30.88912119},
{"learn":[0.2082098668],"iteration":238,"passed_time":9.690837923,"remaining_time":30.85660108},
{"learn":[0.20818765],"iteration":239,"passed_time":9.729481356,"remaining_time":30.8100243},
{"learn":[0.2081641083],"iteration":240,"passed_time":9.769076358,"remaining_time":30.76651019},
{"learn":[0.208137633],"iteration":241,"passed_time":9.807951471,"remaining_time":30.72077362},
{"learn":[0.2080346794],"iteration":242,"passed_time":9.847666984,"remaining_time":30.67771155},
{"learn":[0.2080091133],"iteration":243,"passed_time":9.88596821,"remaining_time":30.63029494},
{"learn":[0.2079837062],"iteration":244,"passed_time":9.926474937,"remaining_time":30.5897493},
{"learn":[0.2078736916],"iteration":245,"passed_time":9.964782243,"remaining_time":30.54246265},
{"learn":[0.2078465513],"iteration":246,"passed_time":10.00369734,"remaining_time":30.49710162},
{"learn":[0.2078224284],"iteration":247,"passed_time":10.04313543,"remaining_time":30.45337839},
{"learn":[0.2077947782],"iteration":248,"passed_time":10.08108541,"remaining_time":30.40520139},
{"learn":[0.2076927236],"iteration":249,"passed_time":10.12435978,"remaining_time":30.37307935},
{"learn":[0.2076720721],"iteration":250,"passed_time":10.1645061,"remaining_time":30.33153414},
{"learn":[0.2076508573],"iteration":251,"passed_time":10.2029526,"remaining_time":30.28495454},
{"learn":[0.2075400073],"iteration":252,"passed_time":10.24196631,"remaining_time":30.24011398},
{"learn":[0.2074107679],"iteration":253,"passed_time":10.28123868,"remaining_time":30.19607896},
{"learn":[0.2073862152],"iteration":254,"passed_time":10.32134226,"remaining_time":30.15450974},
{"learn":[0.2073620237],"iteration":255,"passed_time":10.36156843,"remaining_time":30.11330824},
{"learn":[0.2073384654],"iteration":256,"passed_time":10.40352027,"remaining_time":30.07710334},
{"learn":[0.2072092044],"iteration":257,"passed_time":10.4439506,"remaining_time":30.03647808},
{"learn":[0.2071909815],"iteration":258,"passed_time":10.48325811,"remaining_time":29.99264192},
{"learn":[0.2071649335],"iteration":259,"passed_time":10.52179089,"remaining_time":29.94663561},
{"learn":[0.2071434135],"iteration":260,"passed_time":10.56156599,"remaining_time":29.90420408},
{"learn":[0.2071169701],"iteration":261,"passed_time":10.60140489,"remaining_time":29.86197255},
{"learn":[0.207081131],"iteration":262,"passed_time":10.64281305,"remaining_time":29.82415673},
{"learn":[0.2070548655],"iteration":263,"passed_time":10.68027256,"remaining_time":29.77530533},
{"learn":[0.2070283101],"iteration":264,"passed_time":10.71907058,"remaining_time":29.73025235},
{"learn":[0.2070026995],"iteration":265,"passed_time":10.75556822,"remaining_time":29.67889877},
{"learn":[0.2069777196],"iteration":266,"passed_time":10.79498125,"remaining_time":29.63566015},
{"learn":[0.2069533501],"iteration":267,"passed_time":10.83754926,"remaining_time":29.60106737},
{"learn":[0.2068211479],"iteration":268,"passed_time":10.88565112,"remaining_time":29.58145341},
{"learn":[0.2067955246],"iteration":269,"passed_time":10.92517373,"remaining_time":29.53843266},
{"learn":[0.2067723986],"iteration":270,"passed_time":10.96265135,"remaining_time":29.48993665},
{"learn":[0.2067473551],"iteration":271,"passed_time":10.99948428,"remaining_time":29.43979616},
{"learn":[0.2067246793],"iteration":272,"passed_time":11.03867268,"remaining_time":29.39602578},
{"learn":[0.2065310084],"iteration":273,"passed_time":11.08095604,"remaining_time":29.36048937},
{"learn":[0.2065066249],"iteration":274,"passed_time":11.1231536,"remaining_time":29.32467768},
{"learn":[0.2064821955],"iteration":275,"passed_time":11.1606481,"remaining_time":29.2764827},
{"learn":[0.2063430201],"iteration":276,"passed_time":11.1995323,"remaining_time":29.23199224},
{"learn":[0.2063193372],"iteration":277,"passed_time":11.23762048,"remaining_time":29.18547478},
{"learn":[0.2062946256],"iteration":278,"passed_time":11.27538922,"remaining_time":29.13819221},
{"learn":[0.2062698199],"iteration":279,"passed_time":11.31376008,"remaining_time":29.09252591},
{"learn":[0.2062476387],"iteration":280,"passed_time":11.352528,"remaining_time":29.04792752},
{"learn":[0.2060260188],"iteration":281,"passed_time":11.39386377,"remaining_time":29.00990847},
{"learn":[0.205910099],"iteration":282,"passed_time":11.43512137,"remaining_time":28.97166792},
{"learn":[0.2057695312],"iteration":283,"passed_time":11.47395328,"remaining_time":28.92729067},
{"learn":[0.2057456296],"iteration":284,"passed_time":11.5118367,"remaining_time":28.88057278},
{"learn":[0.2057237422],"iteration":285,"passed_time":11.55110043,"remaining_time":28.83736262},
{"learn":[0.205700545],"iteration":286,"passed_time":11.59219447,"remaining_time":28.79872704},
{"learn":[0.2056763204],"iteration":287,"passed_time":11.63135937,"remaining_time":28.75530512},
{"learn":[0.2055220591],"iteration":288,"passed_time":11.67026182,"remaining_time":28.71126697},
{"learn":[0.2054983304],"iteration":289,"passed_time":11.70895966,"remaining_time":28.66676331},
{"learn":[0.2053404388],"iteration":290,"passed_time":11.74723274,"remaining_time":28.62126465},
{"learn":[0.2053181063],"iteration":291,"passed_time":11.78711845,"remaining_time":28.57972555},
{"learn":[0.2050941124],"iteration":292,"passed_time":11.83166785,"remaining_time":28.5494511},
{"learn":[0.2050717545],"iteration":293,"passed_time":11.86872875,"remaining_time":28.50109694},
{"learn":[0.2049140205],"iteration":294,"passed_time":11.90834232,"remaining_time":28.45891977},
{"learn":[0.2048897476],"iteration":295,"passed_time":11.94487398,"remaining_time":28.40943},
{"learn":[0.2048665123],"iteration":296,"passed_time":11.98289766,"remaining_time":28.3635591},
{"learn":[0.2047727178],"iteration":297,"passed_time":12.0220637,"remaining_time":28.32043195},
{"learn":[0.2046650416],"iteration":298,"passed_time":12.06426593,"remaining_time":28.28444956},
{"learn":[0.2045437851],"iteration":299,"passed_time":12.10485444,"remaining_time":28.24466037},
{"learn":[0.2045213064],"iteration":300,"passed_time":12.14170554,"remaining_time":28.19618661},
{"learn":[0.2043764254],"iteration":301,"passed_time":12.18111766,"remaining_time":28.15370902},
{"learn":[0.2042594172],"iteration":302,"passed_time":12.22029988,"remaining_time":28.11072283},
{"learn":[0.2041369743],"iteration":303,"passed_time":12.26102008,"remaining_time":28.07128282},
{"learn":[0.2040053024],"iteration":304,"passed_time":12.30486011,"remaining_time":28.03894353},
{"learn":[0.2038234584],"iteration":305,"passed_time":12.3468151,"remaining_time":28.00225386},
{"learn":[0.2038013191],"iteration":306,"passed_time":12.38585567,"remaining_time":27.95895108},
{"learn":[0.2036390928],"iteration":307,"passed_time":12.42654867,"remaining_time":27.91938858},
{"learn":[0.2033465106],"iteration":308,"passed_time":12.46626594,"remaining_time":27.87763679},
{"learn":[0.2030980682],"iteration":309,"passed_time":12.51157166,"remaining_time":27.84833692},
{"learn":[0.2029568189],"iteration":310,"passed_time":12.55366673,"remaining_time":27.81182116},
{"learn":[0.2028365987],"iteration":311,"passed_time":12.59236158,"remaining_time":27.7677717},
{"learn":[0.2026809578],"iteration":312,"passed_time":12.63413833,"remaining_time":27.73052087},
{"learn":[0.2024694494],"iteration":313,"passed_time":12.67394785,"remaining_time":27.68894339},
{"learn":[0.2024470011],"iteration":314,"passed_time":12.71387235,"remaining_time":27.64762718},
{"learn":[0.2022772573],"iteration":315,"passed_time":12.754794,"remaining_time":27.60847816},
{"learn":[0.2022559319],"iteration":316,"passed_time":12.79358424,"remaining_time":27.56472567},
{"learn":[0.20213141],"iteration":317,"passed_time":12.83358855,"remaining_time":27.52360815},
{"learn":[0.2019600054],"iteration":318,"passed_time":12.87332692,"remaining_time":27.48192988},
{"learn":[0.2017693965],"iteration":319,"passed_time":12.91779755,"remaining_time":27.45031978},
{"learn":[0.2016485723],"iteration":320,"passed_time":12.96136266,"remaining_time":27.41671416},
{"learn":[0.2015423228],"iteration":321,"passed_time":13.00031104,"remaining_time":27.37332574},
{"learn":[0.2014390907],"iteration":322,"passed_time":13.04022051,"remaining_time":27.3319792},
{"learn":[0.2012424253],"iteration":323,"passed_time":13.07979362,"remaining_time":27.28993979},
{"learn":[0.2010631561],"iteration":324,"passed_time":13.11892649,"remaining_time":27.24700117},
{"learn":[0.2010407626],"iteration":325,"passed_time":13.15829474,"remaining_time":27.20457255},
{"learn":[0.2008337682],"iteration":326,"passed_time":13.20072924,"remaining_time":27.16847332},
{"learn":[0.200667024],"iteration":327,"passed_time":13.24222056,"remaining_time":27.1304031},
{"learn":[0.2004453672],"iteration":328,"passed_time":13.28282692,"remaining_time":27.09050718},
{"learn":[0.2002288017],"iteration":329,"passed_time":13.32297445,"remaining_time":27.0496754},
{"learn":[0.2000272382],"iteration":330,"passed_time":13.36365311,"remaining_time":27.00992124},
{"learn":[0.1998589973],"iteration":331,"passed_time":13.40623121,"remaining_time":26.97398327},
{"learn":[0.1998357455],"iteration":332,"passed_time":13.44647758,"remaining_time":26.93333498},
{"learn":[0.1997209778],"iteration":333,"passed_time":13.48584881,"remaining_time":26.89094403},
{"learn":[0.1996976611],"iteration":334,"passed_time":13.52550639,"remaining_time":26.84913955},
{"learn":[0.1995448481],"iteration":335,"passed_time":13.57035533,"remaining_time":26.81760695},
{"learn":[0.1995235036],"iteration":336,"passed_time":13.61027442,"remaining_time":26.77629656},
{"learn":[0.19943706],"iteration":337,"passed_time":13.6529116,"remaining_time":26.74031799},
{"learn":[0.1992893486],"iteration":338,"passed_time":13.69393935,"remaining_time":26.70116197},
{"learn":[0.1991265195],"iteration":339,"passed_time":13.73329748,"remaining_time":26.65875393},
{"learn":[0.1990068029],"iteration":340,"passed_time":13.77469312,"remaining_time":26.62030137},
{"learn":[0.1989249738],"iteration":341,"passed_time":13.81622377,"remaining_time":26.58209135},
{"learn":[0.1986991348],"iteration":342,"passed_time":13.85875177,"remaining_time":26.54577234},
{"learn":[0.1984435565],"iteration":343,"passed_time":13.90078805,"remaining_time":26.50847953},
{"learn":[0.1984219729],"iteration":344,"passed_time":13.93744971,"remaining_time":26.46095525},
{"learn":[0.1982981071],"iteration":345,"passed_time":13.97666097,"remaining_time":26.41831293},
{"learn":[0.1981549772],"iteration":346,"passed_time":14.01773734,"remaining_time":26.37920024},
{"learn":[0.1980499293],"iteration":347,"passed_time":14.05931,"remaining_time":26.3410061},
{"learn":[0.1979617081],"iteration":348,"passed_time":14.09906785,"remaining_time":26.29940736},
{"learn":[0.1979395688],"iteration":349,"passed_time":14.13689971,"remaining_time":26.25424232},
{"learn":[0.1977121099],"iteration":350,"passed_time":14.17782624,"remaining_time":26.2148411},
{"learn":[0.1975516663],"iteration":351,"passed_time":14.21988476,"remaining_time":26.17751513},
{"learn":[0.197530805],"iteration":352,"passed_time":14.25948708,"remaining_time":26.13566046},
{"learn":[0.1974182383],"iteration":353,"passed_time":14.30259026,"remaining_time":26.10020708},
{"learn":[0.1973344663],"iteration":354,"passed_time":14.34228273,"remaining_time":26.05851368},
{"learn":[0.1971794345],"iteration":355,"passed_time":14.38370154,"remaining_time":26.01995447},
{"learn":[0.1971581421],"iteration":356,"passed_time":14.42347595,"remaining_time":25.97841746},
{"learn":[0.197137441],"iteration":357,"passed_time":14.46329811,"remaining_time":25.93697594},
{"learn":[0.1971176643],"iteration":358,"passed_time":14.50581974,"remaining_time":25.90036338},
{"learn":[0.1969360886],"iteration":359,"passed_time":14.54644511,"remaining_time":25.86034687},
{"learn":[0.1968309975],"iteration":360,"passed_time":14.58672514,"remaining_time":25.81971569},
{"learn":[0.1966969058],"iteration":361,"passed_time":14.62783804,"remaining_time":25.78055433},
{"learn":[0.1965393054],"iteration":362,"passed_time":14.66772195,"remaining_time":25.73922557},
{"learn":[0.1964459839],"iteration":363,"passed_time":14.71061123,"remaining_time":25.70315589},
{"learn":[0.1963215828],"iteration":364,"passed_time":14.75339212,"remaining_time":25.66686027},
{"learn":[0.1963023923],"iteration":365,"passed_time":14.79236274,"remaining_time":25.6239289},
{"learn":[0.1961552798],"iteration":366,"passed_time":14.83427483,"remaining_time":25.58609255},
{"learn":[0.1960132764],"iteration":367,"passed_time":14.87323236,"remaining_time":25.54315992},
{"learn":[0.1959032962],"iteration":368,"passed_time":14.9138805,"remaining_time":25.50313982},
{"learn":[0.1958087489],"iteration":369,"passed_time":14.95461845,"remaining_time":25.46326925},
{"learn":[0.1957105586],"iteration":370,"passed_time":14.99517721,"remaining_time":25.42309019},
{"learn":[0.1956900317],"iteration":371,"passed_time":15.03415757,"remaining_time":25.3802445},
{"learn":[0.1956697515],"iteration":372,"passed_time":15.07061818,"remaining_time":25.33318391},
{"learn":[0.1954506404],"iteration":373,"passed_time":15.11111182,"remaining_time":25.29293047},
{"learn":[0.1953519033],"iteration":374,"passed_time":15.15175885,"remaining_time":25.25293142},
{"learn":[0.195268383],"iteration":375,"passed_time":15.19156249,"remaining_time":25.21152924},
{"learn":[0.1951415876],"iteration":376,"passed_time":15.23596825,"remaining_time":25.17774064},
{"learn":[0.1950420507],"iteration":377,"passed_time":15.2740391,"remaining_time":25.13347175},
{"learn":[0.1950227153],"iteration":378,"passed_time":15.31332301,"remaining_time":25.09122319},
{"learn":[0.194879467],"iteration":379,"passed_time":15.35242721,"remaining_time":25.04869702},
{"learn":[0.194749588],"iteration":380,"passed_time":15.39062782,"remaining_time":25.00472079},
{"learn":[0.1946625659],"iteration":381,"passed_time":15.43596542,"remaining_time":24.97232103},
{"learn":[0.1946438001],"iteration":382,"passed_time":15.47558994,"remaining_time":24.93065011},
{"learn":[0.1944867961],"iteration":383,"passed_time":15.51668634,"remaining_time":24.89135101},
{"learn":[0.1943750127],"iteration":384,"passed_time":15.55893983,"remaining_time":24.8538909},
{"learn":[0.1941698812],"iteration":385,"passed_time":15.60046074,"remaining_time":24.81524065},
{"learn":[0.1940906169],"iteration":386,"passed_time":15.63941121,"remaining_time":24.77250407},
{"learn":[0.1940709279],"iteration":387,"passed_time":15.67975427,"remaining_time":24.73198354},
{"learn":[0.1939531542],"iteration":388,"passed_time":15.72160828,"remaining_time":24.69383718},
{"learn":[0.193934138],"iteration":389,"passed_time":15.76048536,"remaining_time":24.65101556},
{"learn":[0.1937402738],"iteration":390,"passed_time":15.8005954,"remaining_time":24.61013453},
{"learn":[0.1935422529],"iteration":391,"passed_time":15.84114111,"remaining_time":24.56993315},
{"learn":[0.1934211057],"iteration":392,"passed_time":15.88044483,"remaining_time":24.52781174},
{"learn":[0.1933249919],"iteration":393,"passed_time":15.92403014,"remaining_time":24.49229001},
{"learn":[0.1931713181],"iteration":394,"passed_time":15.96834282,"remaining_time":24.45784153},
{"learn":[0.192959521],"iteration":395,"passed_time":16.00775854,"remaining_time":24.41587414},
{"learn":[0.1927968941],"iteration":396,"passed_time":16.04711681,"remaining_time":24.37383234},
{"learn":[0.1927775459],"iteration":397,"passed_time":16.08504152,"remaining_time":24.32963566},
{"learn":[0.1927583199],"iteration":398,"passed_time":16.12222726,"remaining_time":24.28435736},
{"learn":[0.1926333733],"iteration":399,"passed_time":16.16591779,"remaining_time":24.24887669},
{"learn":[0.1925601095],"iteration":400,"passed_time":16.20690418,"remaining_time":24.20931573},
{"learn":[0.1923929367],"iteration":401,"passed_time":16.24733951,"remaining_time":24.16892793},
{"learn":[0.192374354],"iteration":402,"passed_time":16.28723481,"remaining_time":24.12773991},
{"learn":[0.1921631419],"iteration":403,"passed_time":16.32681224,"remaining_time":24.08608934},
{"learn":[0.1920534325],"iteration":404,"passed_time":16.36713352,"remaining_time":24.04554183},
{"learn":[0.191868187],"iteration":405,"passed_time":16.41006511,"remaining_time":24.00881447},
{"learn":[0.1918000145],"iteration":406,"passed_time":16.45020529,"remaining_time":23.96798953},
{"learn":[0.1916919899],"iteration":407,"passed_time":16.49051341,"remaining_time":23.92741161},
{"learn":[0.1916102702],"iteration":408,"passed_time":16.52794074,"remaining_time":23.88267231},
{"learn":[0.1915912882],"iteration":409,"passed_time":16.56598285,"remaining_time":23.83885337},
{"learn":[0.1914602903],"iteration":410,"passed_time":16.60710543,"remaining_time":23.79947712},
{"learn":[0.1914415588],"iteration":411,"passed_time":16.64545236,"remaining_time":23.75613104},
{"learn":[0.1912442996],"iteration":412,"passed_time":16.68954053,"remaining_time":23.72096923},
{"learn":[0.1911034902],"iteration":413,"passed_time":16.72852082,"remaining_time":23.6785343},
{"learn":[0.1910853526],"iteration":414,"passed_time":16.76723287,"remaining_time":23.63573791},
{"learn":[0.1909978485],"iteration":415,"passed_time":16.80781195,"remaining_time":23.59558216},
{"learn":[0.1909794083],"iteration":416,"passed_time":16.84513494,"remaining_time":23.55087211},
{"learn":[0.1908743451],"iteration":417,"passed_time":16.88662309,"remaining_time":23.51199674},
{"learn":[0.1907631137],"iteration":418,"passed_time":16.92811804,"remaining_time":23.47311833},
{"learn":[0.1906578153],"iteration":419,"passed_time":16.9688823,"remaining_time":23.43321842},
{"learn":[0.1905913849],"iteration":420,"passed_time":17.00706397,"remaining_time":23.38976257},
{"learn":[0.1904804662],"iteration":421,"passed_time":17.04502153,"remaining_time":23.34602475},
{"learn":[0.1904627406],"iteration":422,"passed_time":17.08257499,"remaining_time":23.30176305},
{"learn":[0.1904445381],"iteration":423,"passed_time":17.12014234,"remaining_time":23.25755185},
{"learn":[0.1903485629],"iteration":424,"passed_time":17.16543023,"remaining_time":23.22381737},
{"learn":[0.1902652016],"iteration":425,"passed_time":17.20475305,"remaining_time":23.18199119},
{"learn":[0.1902472636],"iteration":426,"passed_time":17.24179955,"remaining_time":23.13712212},
{"learn":[0.190230175],"iteration":427,"passed_time":17.27970596,"remaining_time":23.09343881},
{"learn":[0.1901145503],"iteration":428,"passed_time":17.31995912,"remaining_time":23.05290596},
{"learn":[0.1900238724],"iteration":429,"passed_time":17.36314138,"remaining_time":23.01625718},
{"learn":[0.1900061976],"iteration":430,"passed_time":17.40412017,"remaining_time":22.97666909},
{"learn":[0.1899091835],"iteration":431,"passed_time":17.44314853,"remaining_time":22.93451011},
{"learn":[0.1898920848],"iteration":432,"passed_time":17.48263388,"remaining_time":22.89296399},
{"learn":[0.1898007596],"iteration":433,"passed_time":17.521182,"remaining_time":22.85020509},
{"learn":[0.1896704254],"iteration":434,"passed_time":17.56143965,"remaining_time":22.80968598},
{"learn":[0.1896530202],"iteration":435,"passed_time":17.60372273,"remaining_time":22.77178811},
{"learn":[0.1896356379],"iteration":436,"passed_time":17.64396958,"remaining_time":22.73124685},
{"learn":[0.1894441859],"iteration":437,"passed_time":17.68444132,"remaining_time":22.69099548},
{"learn":[0.1894268659],"iteration":438,"passed_time":17.72227417,"remaining_time":22.64737087},
{"learn":[0.1893094457],"iteration":439,"passed_time":17.76363267,"remaining_time":22.60825976},
{"learn":[0.1892929153],"iteration":440,"passed_time":17.80168083,"remaining_time":22.56494237},
{"learn":[0.1891837018],"iteration":441,"passed_time":17.84156205,"remaining_time":22.52396295},
{"learn":[0.189039107],"iteration":442,"passed_time":17.88660322,"remaining_time":22.48947628},
{"learn":[0.1890221062],"iteration":443,"passed_time":17.92441489,"remaining_time":22.44588891},
{"learn":[0.1888421237],"iteration":444,"passed_time":17.96500977,"remaining_time":22.4057987},
{"learn":[0.1888252258],"iteration":445,"passed_time":18.00292559,"remaining_time":22.36237843},
{"learn":[0.18870718],"iteration":446,"passed_time":18.04136039,"remaining_time":22.31962482},
{"learn":[0.1885726941],"iteration":447,"passed_time":18.08434408,"remaining_time":22.28249539},
{"learn":[0.18847907],"iteration":448,"passed_time":18.12521117,"remaining_time":22.24274244},
{"learn":[0.1882708753],"iteration":449,"passed_time":18.16734257,"remaining_time":22.2045298},
{"learn":[0.1880986226],"iteration":450,"passed_time":18.20702344,"remaining_time":22.16331678},
{"learn":[0.1879525808],"iteration":451,"passed_time":18.24719606,"remaining_time":22.12270673},
{"learn":[0.1878497416],"iteration":452,"passed_time":18.28692977,"remaining_time":22.08156862},
{"learn":[0.1878333511],"iteration":453,"passed_time":18.32722815,"remaining_time":22.0411158},
{"learn":[0.1875875575],"iteration":454,"passed_time":18.37285157,"remaining_time":22.00704198},
{"learn":[0.187571715],"iteration":455,"passed_time":18.41155036,"remaining_time":21.96465657},
{"learn":[0.1873820992],"iteration":456,"passed_time":18.45031747,"remaining_time":21.92236847},
{"learn":[0.1872628047],"iteration":457,"passed_time":18.49000197,"remaining_time":21.88118137},
{"learn":[0.1871156228],"iteration":458,"passed_time":18.53232973,"remaining_time":21.8431163},
{"learn":[0.1870990257],"iteration":459,"passed_time":18.57206872,"remaining_time":21.80199372},
{"learn":[0.1870825672],"iteration":460,"passed_time":18.61153209,"remaining_time":21.76055488},
{"learn":[0.1869610583],"iteration":461,"passed_time":18.64974678,"remaining_time":21.7176705},
{"learn":[0.1867832731],"iteration":462,"passed_time":18.69063815,"remaining_time":21.67791077},
{"learn":[0.1867672189],"iteration":463,"passed_time":18.72789831,"remaining_time":21.63395149},
{"learn":[0.1866563428],"iteration":464,"passed_time":18.76796988,"remaining_time":21.59325567},
{"learn":[0.1866414502],"iteration":465,"passed_time":18.80840553,"remaining_time":21.55297973},
{"learn":[0.1865183792],"iteration":466,"passed_time":18.84819487,"remaining_time":21.51196546},
{"learn":[0.1865027835],"iteration":467,"passed_time":18.88749845,"remaining_time":21.47040422},
{"learn":[0.1863866901],"iteration":468,"passed_time":18.92638519,"remaining_time":21.42838067},
{"learn":[0.1862215157],"iteration":469,"passed_time":18.96595857,"remaining_time":21.38714477},
{"learn":[0.1861373723],"iteration":470,"passed_time":19.00708359,"remaining_time":21.34765864},
{"learn":[0.1860554326],"iteration":471,"passed_time":19.0488154,"remaining_time":21.30884434},
{"learn":[0.1858979626],"iteration":472,"passed_time":19.08963076,"remaining_time":21.26899663},
{"learn":[0.1857377243],"iteration":473,"passed_time":19.12883333,"remaining_time":21.22735513},
{"learn":[0.1857217452],"iteration":474,"passed_time":19.16742891,"remaining_time":21.185053},
{"learn":[0.1855953375],"iteration":475,"passed_time":19.2063602,"remaining_time":21.14313602},
{"learn":[0.1854679775],"iteration":476,"passed_time":19.2474074,"remaining_time":21.10355151},
{"learn":[0.1853251597],"iteration":477,"passed_time":19.29017695,"remaining_time":21.06584177},
{"learn":[0.1852149645],"iteration":478,"passed_time":19.32958967,"remaining_time":21.02445975},
{"learn":[0.1850617924],"iteration":479,"passed_time":19.36961752,"remaining_time":20.98375231},
{"learn":[0.1850212841],"iteration":480,"passed_time":19.41000622,"remaining_time":20.94343707},
{"learn":[0.1850054334],"iteration":481,"passed_time":19.44850639,"remaining_time":20.90109193},
{"learn":[0.184989741],"iteration":482,"passed_time":19.48951706,"remaining_time":20.86144994},
{"learn":[0.1848574333],"iteration":483,"passed_time":19.53075561,"remaining_time":20.82204524},
{"learn":[0.1847280833],"iteration":484,"passed_time":19.568876,"remaining_time":20.77932193},
{"learn":[0.1847129612],"iteration":485,"passed_time":19.60851951,"remaining_time":20.73822845},
{"learn":[0.1846054853],"iteration":486,"passed_time":19.64622182,"remaining_time":20.69509609},
{"learn":[0.1845419413],"iteration":487,"passed_time":19.68596401,"remaining_time":20.65412617},
{"learn":[0.1844309305],"iteration":488,"passed_time":19.72618279,"remaining_time":20.61365931},
{"learn":[0.1843219407],"iteration":489,"passed_time":19.76919211,"remaining_time":20.57609792},
{"learn":[0.1843064245],"iteration":490,"passed_time":19.81020493,"remaining_time":20.53644462},
{"learn":[0.1842918434],"iteration":491,"passed_time":19.84721812,"remaining_time":20.49265611},
{"learn":[0.1842769502],"iteration":492,"passed_time":19.88620614,"remaining_time":20.45092599},
{"learn":[0.1841811918],"iteration":493,"passed_time":19.92474518,"remaining_time":20.40874709},
{"learn":[0.184072745],"iteration":494,"passed_time":19.96622028,"remaining_time":20.36957826},
{"learn":[0.1840580635],"iteration":495,"passed_time":20.00716708,"remaining_time":20.32986332},
{"learn":[0.1839299323],"iteration":496,"passed_time":20.04835091,"remaining_time":20.29038331},
{"learn":[0.1838560079],"iteration":497,"passed_time":20.08828877,"remaining_time":20.24964049},
{"learn":[0.1837609126],"iteration":498,"passed_time":20.12769971,"remaining_time":20.20837186},
{"learn":[0.1836414318],"iteration":499,"passed_time":20.16690526,"remaining_time":20.16690526},
{"learn":[0.1835687682],"iteration":500,"passed_time":20.20931744,"remaining_time":20.12864152},
{"learn":[0.1835537186],"iteration":501,"passed_time":20.24870653,"remaining_time":20.08736226},
{"learn":[0.1834170837],"iteration":502,"passed_time":20.2902259,"remaining_time":20.04819537},
{"learn":[0.1832556152],"iteration":503,"passed_time":20.32981059,"remaining_time":20.00711518},
{"learn":[0.1831760852],"iteration":504,"passed_time":20.36824289,"remaining_time":19.96491135},
{"learn":[0.1830594667],"iteration":505,"passed_time":20.40860958,"remaining_time":19.92461094},
{"learn":[0.1829836877],"iteration":506,"passed_time":20.45048232,"remaining_time":19.88577472},
{"learn":[0.1828630854],"iteration":507,"passed_time":20.49661684,"remaining_time":19.85105411},
{"learn":[0.1828485877],"iteration":508,"passed_time":20.53462711,"remaining_time":19.80845169},
{"learn":[0.1828337409],"iteration":509,"passed_time":20.57130166,"remaining_time":19.76458395},
{"learn":[0.1827341379],"iteration":510,"passed_time":20.61422764,"remaining_time":19.72672665},
{"learn":[0.1826141529],"iteration":511,"passed_time":20.65463146,"remaining_time":19.68644562},
{"learn":[0.1825108299],"iteration":512,"passed_time":20.69687821,"remaining_time":19.64791362},
{"learn":[0.1824960079],"iteration":513,"passed_time":20.73612481,"remaining_time":19.60653046},
{"learn":[0.1823510736],"iteration":514,"passed_time":20.77462523,"remaining_time":19.56445289},
{"learn":[0.1822093277],"iteration":515,"passed_time":20.81715767,"remaining_time":19.52617115},
{"learn":[0.1821946316],"iteration":516,"passed_time":20.85438005,"remaining_time":19.48291212},
{"learn":[0.1821184502],"iteration":517,"passed_time":20.89699254,"remaining_time":19.4446919},
{"learn":[0.1821038761],"iteration":518,"passed_time":20.93736668,"remaining_time":19.4043803},
{"learn":[0.1820894121],"iteration":519,"passed_time":20.9741584,"remaining_time":19.3607616},
{"learn":[0.1820750491],"iteration":520,"passed_time":21.0131464,"remaining_time":19.31918835},
{"learn":[0.1819767729],"iteration":521,"passed_time":21.05213779,"remaining_time":19.27762809},
{"learn":[0.1818400784],"iteration":522,"passed_time":21.09212001,"remaining_time":19.23698135},
{"learn":[0.1817513065],"iteration":523,"passed_time":21.13123896,"remaining_time":19.19555295},
{"learn":[0.1816031532],"iteration":524,"passed_time":21.17253792,"remaining_time":19.15610573},
{"learn":[0.1814783077],"iteration":525,"passed_time":21.21350787,"remaining_time":19.116355},
{"learn":[0.181393692],"iteration":526,"passed_time":21.25251447,"remaining_time":19.07483747},
{"learn":[0.1813794359],"iteration":527,"passed_time":21.29090757,"remaining_time":19.03278101},
{"learn":[0.1812920354],"iteration":528,"passed_time":21.3299311,"remaining_time":18.99129971},
{"learn":[0.1811920153],"iteration":529,"passed_time":21.36978681,"remaining_time":18.95056567},
{"learn":[0.1811777782],"iteration":530,"passed_time":21.41115682,"remaining_time":18.9111724},
{"learn":[0.1810018813],"iteration":531,"passed_time":21.45255529,"remaining_time":18.87179675},
{"learn":[0.1808621775],"iteration":532,"passed_time":21.49182919,"remaining_time":18.83055203},
{"learn":[0.1808484573],"iteration":533,"passed_time":21.52957222,"remaining_time":18.78797875},
{"learn":[0.1806923567],"iteration":534,"passed_time":21.56806259,"remaining_time":18.7460731},
{"learn":[0.1805630671],"iteration":535,"passed_time":21.60958125,"remaining_time":18.70680168},
{"learn":[0.1804515845],"iteration":536,"passed_time":21.65179861,"remaining_time":18.66812432},
{"learn":[0.180291804],"iteration":537,"passed_time":21.69231323,"remaining_time":18.62797158},
{"learn":[0.1801713874],"iteration":538,"passed_time":21.73217387,"remaining_time":18.58725817},
{"learn":[0.1801572851],"iteration":539,"passed_time":21.76899117,"remaining_time":18.54395544},
{"learn":[0.1801433233],"iteration":540,"passed_time":21.81039247,"remaining_time":18.50456589},
{"learn":[0.179986606],"iteration":541,"passed_time":21.85240755,"remaining_time":18.46568756},
{"learn":[0.1798934917],"iteration":542,"passed_time":21.89439389,"remaining_time":18.4267735},
{"learn":[0.1798796018],"iteration":543,"passed_time":21.93241728,"remaining_time":18.38452625},
{"learn":[0.1797545993],"iteration":544,"passed_time":21.97124828,"remaining_time":18.34296875},
{"learn":[0.1796294136],"iteration":545,"passed_time":22.01073247,"remaining_time":18.30196436},
{"learn":[0.1794842542],"iteration":546,"passed_time":22.05135023,"remaining_time":18.2619043},
{"learn":[0.1792547614],"iteration":547,"passed_time":22.0936099,"remaining_time":18.22319649},
{"learn":[0.1792411232],"iteration":548,"passed_time":22.13302593,"remaining_time":18.1821397},
{"learn":[0.179120657],"iteration":549,"passed_time":22.17072894,"remaining_time":18.13968731},
{"learn":[0.1790298074],"iteration":550,"passed_time":22.21091074,"remaining_time":18.09927209},
{"learn":[0.1789702212],"iteration":551,"passed_time":22.24891789,"remaining_time":18.05709278},
{"learn":[0.1788259379],"iteration":552,"passed_time":22.29020454,"remaining_time":18.01757944},
{"learn":[0.1787576078],"iteration":553,"passed_time":22.33309958,"remaining_time":17.97935453},
{"learn":[0.178743728],"iteration":554,"passed_time":22.37081442,"remaining_time":17.93695931},
{"learn":[0.1786100254],"iteration":555,"passed_time":22.4102536,"remaining_time":17.89595791},
{"learn":[0.1785307592],"iteration":556,"passed_time":22.44812162,"remaining_time":17.85371252},
{"learn":[0.1784520645],"iteration":557,"passed_time":22.48578776,"remaining_time":17.81132292},
{"learn":[0.1783781052],"iteration":558,"passed_time":22.52395251,"remaining_time":17.76934357},
{"learn":[0.1783642921],"iteration":559,"passed_time":22.56102166,"remaining_time":17.72651702},
{"learn":[0.1782950236],"iteration":560,"passed_time":22.6013363,"remaining_time":17.68625069},
{"learn":[0.1782313347],"iteration":561,"passed_time":22.63906976,"remaining_time":17.64397252},
{"learn":[0.1781254381],"iteration":562,"passed_time":22.67907067,"remaining_time":17.60347049},
{"learn":[0.178111749],"iteration":563,"passed_time":22.714432,"remaining_time":17.55938361},
{"learn":[0.1780981452],"iteration":564,"passed_time":22.75281574,"remaining_time":17.5176546},
{"learn":[0.178085118],"iteration":565,"passed_time":22.79258705,"remaining_time":17.47700137},
{"learn":[0.177990743],"iteration":566,"passed_time":22.83228031,"remaining_time":17.43629167},
{"learn":[0.1779773178],"iteration":567,"passed_time":22.8705949,"remaining_time":17.39453697},
{"learn":[0.1778138466],"iteration":568,"passed_time":22.90949214,"remaining_time":17.3532357},
{"learn":[0.1778005581],"iteration":569,"passed_time":22.96169414,"remaining_time":17.32197979},
{"learn":[0.1777617194],"iteration":570,"passed_time":23.00633461,"remaining_time":17.28496943},
{"learn":[0.1776720212],"iteration":571,"passed_time":23.04784524,"remaining_time":17.24559049},
{"learn":[0.1776585089],"iteration":572,"passed_time":23.08601984,"remaining_time":17.2037181},
{"learn":[0.1775787589],"iteration":573,"passed_time":23.12495143,"remaining_time":17.1624204},
{"learn":[0.1775672963],"iteration":574,"passed_time":23.16278106,"remaining_time":17.12031644},
{"learn":[0.1774380538],"iteration":575,"passed_time":23.20465915,"remaining_time":17.08120743},
{"learn":[0.1774255346],"iteration":576,"passed_time":23.24436584,"remaining_time":17.04049697},
{"learn":[0.1774126129],"iteration":577,"passed_time":23.285437,"remaining_time":17.00078619},
{"learn":[0.1773062522],"iteration":578,"passed_time":23.3260576,"remaining_time":16.96074309},
{"learn":[0.1772933051],"iteration":579,"passed_time":23.36249724,"remaining_time":16.91767042},
{"learn":[0.1771805331],"iteration":580,"passed_time":23.40336229,"remaining_time":16.87781205},
{"learn":[0.1770338879],"iteration":581,"passed_time":23.44310713,"remaining_time":16.83714567},
{"learn":[0.176900643],"iteration":582,"passed_time":23.48538216,"remaining_time":16.79829221},
{"learn":[0.176887689],"iteration":583,"passed_time":23.52577133,"remaining_time":16.75808369},
{"learn":[0.1767329248],"iteration":584,"passed_time":23.56471922,"remaining_time":16.7168521},
{"learn":[0.176622406],"iteration":585,"passed_time":23.60444533,"remaining_time":16.6761781},
{"learn":[0.1764906693],"iteration":586,"passed_time":23.64426182,"remaining_time":16.63557092},
{"learn":[0.1764779154],"iteration":587,"passed_time":23.68256296,"remaining_time":16.59390466},
{"learn":[0.1763804207],"iteration":588,"passed_time":23.72176092,"remaining_time":16.55287562},
{"learn":[0.1762044601],"iteration":589,"passed_time":23.76314458,"remaining_time":16.51337166},
{"learn":[0.1760586745],"iteration":590,"passed_time":23.8060921,"remaining_time":16.4749436},
{"learn":[0.176045723],"iteration":591,"passed_time":23.84327617,"remaining_time":16.43252817},
{"learn":[0.175964234],"iteration":592,"passed_time":23.88415107,"remaining_time":16.39266355},
{"learn":[0.1758884595],"iteration":593,"passed_time":23.92354225,"remaining_time":16.35178141},
{"learn":[0.1758758589],"iteration":594,"passed_time":23.96462349,"remaining_time":16.31205465},
{"learn":[0.1757490889],"iteration":595,"passed_time":24.00727717,"remaining_time":16.27338922},
{"learn":[0.1757365882],"iteration":596,"passed_time":24.04435357,"remaining_time":16.23094554},
{"learn":[0.1756176777],"iteration":597,"passed_time":24.08316957,"remaining_time":16.18968924},
{"learn":[0.1756052513],"iteration":598,"passed_time":24.12041449,"remaining_time":16.14738933},
{"learn":[0.1755208448],"iteration":599,"passed_time":24.15843663,"remaining_time":16.10562442},
{"learn":[0.1753788802],"iteration":600,"passed_time":24.20276345,"remaining_time":16.06805759},
{"learn":[0.1753665873],"iteration":601,"passed_time":24.24366513,"remaining_time":16.02820385},
{"learn":[0.175354311],"iteration":602,"passed_time":24.28185114,"remaining_time":15.98655871},
{"learn":[0.1752399877],"iteration":603,"passed_time":24.32070635,"remaining_time":15.94536376},
{"learn":[0.1751506379],"iteration":604,"passed_time":24.36000348,"remaining_time":15.90446508},
{"learn":[0.1750205777],"iteration":605,"passed_time":24.40136541,"remaining_time":15.86491415},
{"learn":[0.1750084686],"iteration":606,"passed_time":24.44135329,"remaining_time":15.82446762},
{"learn":[0.1749964307],"iteration":607,"passed_time":24.48218631,"remaining_time":15.78456749},
{"learn":[0.1748108514],"iteration":608,"passed_time":24.52301469,"remaining_time":15.74466132},
{"learn":[0.1747130547],"iteration":609,"passed_time":24.5613818,"remaining_time":15.70317853},
{"learn":[0.1746466471],"iteration":610,"passed_time":24.60119753,"remaining_time":15.66262821},
{"learn":[0.1745467046],"iteration":611,"passed_time":24.64402902,"remaining_time":15.62399225},
{"learn":[0.1744663963],"iteration":612,"passed_time":24.68535641,"remaining_time":15.58439304},
{"learn":[0.1743810711],"iteration":613,"passed_time":24.73048048,"remaining_time":15.54717502},
{"learn":[0.1742648385],"iteration":614,"passed_time":24.76896229,"remaining_time":15.50577314},
{"learn":[0.1741579819],"iteration":615,"passed_time":24.81124807,"remaining_time":15.46675205},
{"learn":[0.1741133003],"iteration":616,"passed_time":24.8501001,"remaining_time":15.42558888},
{"learn":[0.1739656264],"iteration":617,"passed_time":24.88923683,"remaining_time":15.38460917},
{"learn":[0.1738133151],"iteration":618,"passed_time":24.93450131,"remaining_time":15.34740711},
{"learn":[0.1737783756],"iteration":619,"passed_time":24.97423819,"remaining_time":15.30679115},
{"learn":[0.1737663358],"iteration":620,"passed_time":25.01285999,"remaining_time":15.26549748},
{"learn":[0.1736790435],"iteration":621,"passed_time":25.05210033,"remaining_time":15.22458831},
{"learn":[0.1736674976],"iteration":622,"passed_time":25.08991541,"remaining_time":15.182822},
{"learn":[0.1736227678],"iteration":623,"passed_time":25.13233711,"remaining_time":15.14384415},
{"learn":[0.1735055332],"iteration":624,"passed_time":25.17289454,"remaining_time":15.10373672},
{"learn":[0.1733115292],"iteration":625,"passed_time":25.21370053,"remaining_time":15.06377635},
{"learn":[0.1732202384],"iteration":626,"passed_time":25.25269182,"remaining_time":15.02273373},
{"learn":[0.1730473321],"iteration":627,"passed_time":25.29427594,"remaining_time":14.98323352},
{"learn":[0.1729048977],"iteration":628,"passed_time":25.3343192,"remaining_time":14.94281784},
{"learn":[0.1727918453],"iteration":629,"passed_time":25.37497404,"remaining_time":14.90276253},
{"learn":[0.1727797483],"iteration":630,"passed_time":25.41455793,"remaining_time":14.86207904},
{"learn":[0.172594532],"iteration":631,"passed_time":25.46814442,"remaining_time":14.82955244},
{"learn":[0.1725818456],"iteration":632,"passed_time":25.5064946,"remaining_time":14.78812562},
{"learn":[0.1724955018],"iteration":633,"passed_time":25.54603891,"remaining_time":14.74739786},
{"learn":[0.1724243889],"iteration":634,"passed_time":25.58655046,"remaining_time":14.70722979},
{"learn":[0.1723510106],"iteration":635,"passed_time":25.62700027,"remaining_time":14.66702531},
{"learn":[0.1722368991],"iteration":636,"passed_time":25.67201218,"remaining_time":14.62941981},
{"learn":[0.1721310425],"iteration":637,"passed_time":25.7108176,"remaining_time":14.58826955},
{"learn":[0.172049523],"iteration":638,"passed_time":25.74842317,"remaining_time":14.54644877},
{"learn":[0.1719667511],"iteration":639,"passed_time":25.79117542,"remaining_time":14.50753618},
{"learn":[0.1718081341],"iteration":640,"passed_time":25.83427717,"remaining_time":14.46880734},
{"learn":[0.1716244551],"iteration":641,"passed_time":25.87998585,"remaining_time":14.43151859},
{"learn":[0.1716114686],"iteration":642,"passed_time":25.91824075,"remaining_time":14.39006524},
{"learn":[0.1715997403],"iteration":643,"passed_time":25.95600221,"remaining_time":14.34834905},
{"learn":[0.171544246],"iteration":644,"passed_time":25.99573398,"remaining_time":14.30772955},
{"learn":[0.1713829854],"iteration":645,"passed_time":26.03459357,"remaining_time":14.26663487},
{"learn":[0.1713164342],"iteration":646,"passed_time":26.074738,"remaining_time":14.22624809},
{"learn":[0.1713046907],"iteration":647,"passed_time":26.11425659,"remaining_time":14.1855221},
{"learn":[0.1711170247],"iteration":648,"passed_time":26.15499142,"remaining_time":14.14545761},
{"learn":[0.1709685809],"iteration":649,"passed_time":26.19562578,"remaining_time":14.10533696},
{"learn":[0.1709570643],"iteration":650,"passed_time":26.23310956,"remaining_time":14.06352571},
{"learn":[0.1708879795],"iteration":651,"passed_time":26.27400839,"remaining_time":14.02355049},
{"learn":[0.1708765532],"iteration":652,"passed_time":26.31418542,"remaining_time":13.98318889},
{"learn":[0.1708652356],"iteration":653,"passed_time":26.35468805,"remaining_time":13.9430001},
{"learn":[0.1707291629],"iteration":654,"passed_time":26.3954096,"remaining_time":13.90292567},
{"learn":[0.1707178033],"iteration":655,"passed_time":26.43350465,"remaining_time":13.86147195},
{"learn":[0.1706138566],"iteration":656,"passed_time":26.47406587,"remaining_time":13.82131597},
{"learn":[0.1706026522],"iteration":657,"passed_time":26.5133425,"remaining_time":13.78049109},
{"learn":[0.1705332998],"iteration":658,"passed_time":26.55433347,"remaining_time":13.74055798},
{"learn":[0.1705221748],"iteration":659,"passed_time":26.59441726,"remaining_time":13.70015435},
{"learn":[0.1704105619],"iteration":660,"passed_time":26.63341732,"remaining_time":13.65919587},
{"learn":[0.1703365345],"iteration":661,"passed_time":26.67330478,"remaining_time":13.6186964},
{"learn":[0.1702116464],"iteration":662,"passed_time":26.71250562,"remaining_time":13.57784977},
{"learn":[0.1700846151],"iteration":663,"passed_time":26.7517823,"remaining_time":13.53704646},
{"learn":[0.1699610837],"iteration":664,"passed_time":26.79489508,"remaining_time":13.49818023},
{"learn":[0.1698865801],"iteration":665,"passed_time":26.83640289,"remaining_time":13.45849634},
{"learn":[0.1697687105],"iteration":666,"passed_time":26.87633361,"remaining_time":13.41801963},
{"learn":[0.1697578437],"iteration":667,"passed_time":26.91534532,"remaining_time":13.37708779},
{"learn":[0.1696199036],"iteration":668,"passed_time":26.95431028,"remaining_time":13.33613857},
{"learn":[0.1696088842],"iteration":669,"passed_time":26.9925179,"remaining_time":13.29482225},
{"learn":[0.1695201836],"iteration":670,"passed_time":27.03466106,"remaining_time":13.25544484},
{"learn":[0.1693540109],"iteration":671,"passed_time":27.0826409,"remaining_time":13.21890806},
{"learn":[0.1692517471],"iteration":672,"passed_time":27.12495244,"remaining_time":13.17958313},
{"learn":[0.1692407881],"iteration":673,"passed_time":27.16150796,"remaining_time":13.13746527},
{"learn":[0.1691768767],"iteration":674,"passed_time":27.20032645,"remaining_time":13.09645347},
{"learn":[0.1690457484],"iteration":675,"passed_time":27.24018097,"remaining_time":13.05594473},
{"learn":[0.1689665184],"iteration":676,"passed_time":27.28204758,"remaining_time":13.01639789},
{"learn":[0.1688555361],"iteration":677,"passed_time":27.3265414,"remaining_time":12.97809193},
{"learn":[0.1688446776],"iteration":678,"passed_time":27.36391654,"remaining_time":12.93640237},
{"learn":[0.1687528241],"iteration":679,"passed_time":27.402859,"remaining_time":12.89546306},
{"learn":[0.1686180833],"iteration":680,"passed_time":27.4428252,"remaining_time":12.85500916},
{"learn":[0.1685389582],"iteration":681,"passed_time":27.48419696,"remaining_time":12.81521207},
{"learn":[0.168437479],"iteration":682,"passed_time":27.52633593,"remaining_time":12.77576646},
{"learn":[0.1683891493],"iteration":683,"passed_time":27.5645029,"remaining_time":12.73447795},
{"learn":[0.1683225377],"iteration":684,"passed_time":27.60205606,"remaining_time":12.69291629},
{"learn":[0.1681963005],"iteration":685,"passed_time":27.64236001,"remaining_time":12.65262543},
{"learn":[0.1680014191],"iteration":686,"passed_time":27.68265694,"remaining_time":12.61233133},
{"learn":[0.167990544],"iteration":687,"passed_time":27.72332143,"remaining_time":12.5722039},
{"learn":[0.1679798622],"iteration":688,"passed_time":27.76543885,"remaining_time":12.53273074},
{"learn":[0.1678882726],"iteration":689,"passed_time":27.80465381,"remaining_time":12.49194591},
{"learn":[0.1678776627],"iteration":690,"passed_time":27.84407747,"remaining_time":12.45125896},
{"learn":[0.1677617728],"iteration":691,"passed_time":27.88407008,"remaining_time":12.41082888},
{"learn":[0.1675912088],"iteration":692,"passed_time":27.92537337,"remaining_time":12.3709807},
{"learn":[0.1674746793],"iteration":693,"passed_time":27.96771556,"remaining_time":12.3315864},
{"learn":[0.1674640745],"iteration":694,"passed_time":28.00781853,"remaining_time":12.29120094},
{"learn":[0.1673720036],"iteration":695,"passed_time":28.04687636,"remaining_time":12.25035979},
{"learn":[0.1672608248],"iteration":696,"passed_time":28.08599885,"remaining_time":12.20955187},
{"learn":[0.1672058061],"iteration":697,"passed_time":28.12548525,"remaining_time":12.16890623},
{"learn":[0.167078605],"iteration":698,"passed_time":28.16638244,"remaining_time":12.12887141},
{"learn":[0.1670557569],"iteration":699,"passed_time":28.20635489,"remaining_time":12.08843781},
{"learn":[0.1668720525],"iteration":700,"passed_time":28.24686073,"remaining_time":12.04823304},
{"learn":[0.166716409],"iteration":701,"passed_time":28.29505462,"remaining_time":12.01129099},
{"learn":[0.1666366742],"iteration":702,"passed_time":28.33370303,"remaining_time":11.97028421},
{"learn":[0.1665598132],"iteration":703,"passed_time":28.37385204,"remaining_time":11.92991506},
{"learn":[0.1665055243],"iteration":704,"passed_time":28.41238128,"remaining_time":11.88886876},
{"learn":[0.1664273669],"iteration":705,"passed_time":28.45351457,"remaining_time":11.848914},
{"learn":[0.1662899996],"iteration":706,"passed_time":28.49350002,"remaining_time":11.80848021},
{"learn":[0.1662796701],"iteration":707,"passed_time":28.53174156,"remaining_time":11.76732844},
{"learn":[0.1662691994],"iteration":708,"passed_time":28.56948255,"remaining_time":11.72597944},
{"learn":[0.1662161611],"iteration":709,"passed_time":28.60815034,"remaining_time":11.68501915},
{"learn":[0.1660849279],"iteration":710,"passed_time":28.65178657,"remaining_time":11.64608484},
{"learn":[0.1660745322],"iteration":711,"passed_time":28.68974461,"remaining_time":11.60484052},
{"learn":[0.1659785684],"iteration":712,"passed_time":28.73132728,"remaining_time":11.56506442},
{"learn":[0.1659214274],"iteration":713,"passed_time":28.77107188,"remaining_time":11.524547},
{"learn":[0.165793848],"iteration":714,"passed_time":28.80943488,"remaining_time":11.48348104},
{"learn":[0.1656968104],"iteration":715,"passed_time":28.85348702,"remaining_time":11.44467921},
{"learn":[0.1656865393],"iteration":716,"passed_time":28.89403043,"remaining_time":11.40447784},
{"learn":[0.1656308161],"iteration":717,"passed_time":28.9323429,"remaining_time":11.3633993},
{"learn":[0.1655395158],"iteration":718,"passed_time":28.97146351,"remaining_time":11.32264429},
{"learn":[0.1654444873],"iteration":719,"passed_time":29.01073309,"remaining_time":11.28195176},
{"learn":[0.165291125],"iteration":720,"passed_time":29.05124799,"remaining_time":11.24174506},
{"learn":[0.1652160892],"iteration":721,"passed_time":29.08977936,"remaining_time":11.20077377},
{"learn":[0.1650818062],"iteration":722,"passed_time":29.13231972,"remaining_time":11.16134518},
{"learn":[0.1649469153],"iteration":723,"passed_time":29.17161256,"remaining_time":11.12066998},
{"learn":[0.1649366684],"iteration":724,"passed_time":29.20904835,"remaining_time":11.0792942},
{"learn":[0.1648557561],"iteration":725,"passed_time":29.24945208,"remaining_time":11.03904941},
{"learn":[0.1647831777],"iteration":726,"passed_time":29.29057404,"remaining_time":10.99907388},
{"learn":[0.1647738717],"iteration":727,"passed_time":29.3432862,"remaining_time":10.96342561},
{"learn":[0.1646531881],"iteration":728,"passed_time":29.38659853,"remaining_time":10.92423621},
{"learn":[0.1645818653],"iteration":729,"passed_time":29.42447208,"remaining_time":10.88302392},
{"learn":[0.1645093314],"iteration":730,"passed_time":29.46280861,"remaining_time":10.84199113},
{"learn":[0.1644004396],"iteration":731,"passed_time":29.50382175,"remaining_time":10.80194567},
{"learn":[0.1643041999],"iteration":732,"passed_time":29.54185101,"remaining_time":10.76081067},
{"learn":[0.1641610254],"iteration":733,"passed_time":29.58454505,"remaining_time":10.72137464},
{"learn":[0.1639897016],"iteration":734,"passed_time":29.62817921,"remaining_time":10.68226869},
{"learn":[0.1639795087],"iteration":735,"passed_time":29.66538233,"remaining_time":10.64084366},
{"learn":[0.1638602886],"iteration":736,"passed_time":29.70720401,"remaining_time":10.60107823},
{"learn":[0.1637772706],"iteration":737,"passed_time":29.74576155,"remaining_time":10.56014841},
{"learn":[0.1636980546],"iteration":738,"passed_time":29.78730698,"remaining_time":10.52028027},
{"learn":[0.1636140798],"iteration":739,"passed_time":29.82922112,"remaining_time":10.48053715},
{"learn":[0.1636039804],"iteration":740,"passed_time":29.87072072,"remaining_time":10.44064328},
{"learn":[0.1635486272],"iteration":741,"passed_time":29.91438864,"remaining_time":10.40149901},
{"learn":[0.1634881446],"iteration":742,"passed_time":29.95531457,"remaining_time":10.36139414},
{"learn":[0.1633863207],"iteration":743,"passed_time":29.99609684,"remaining_time":10.32123762},
{"learn":[0.1633311876],"iteration":744,"passed_time":30.03945135,"remaining_time":10.28195986},
{"learn":[0.1632350597],"iteration":745,"passed_time":30.08000268,"remaining_time":10.24171673},
{"learn":[0.1632250309],"iteration":746,"passed_time":30.12059792,"remaining_time":10.20148765},
{"learn":[0.1631672942],"iteration":747,"passed_time":30.15976458,"remaining_time":10.1607763},
{"learn":[0.1630119044],"iteration":748,"passed_time":30.19843383,"remaining_time":10.11990239},
{"learn":[0.1629143435],"iteration":749,"passed_time":30.23892542,"remaining_time":10.07964181},
{"learn":[0.1628389835],"iteration":750,"passed_time":30.27932096,"remaining_time":10.03934876},
{"learn":[0.162690101],"iteration":751,"passed_time":30.32342307,"remaining_time":10.00027782},
{"learn":[0.1626072884],"iteration":752,"passed_time":30.36242107,"remaining_time":9.959519261},
{"learn":[0.1625131321],"iteration":753,"passed_time":30.40074387,"remaining_time":9.918545082},
{"learn":[0.1625035114],"iteration":754,"passed_time":30.44166529,"remaining_time":9.878421186},
{"learn":[0.1623967412],"iteration":755,"passed_time":30.4803638,"remaining_time":9.837577734},
{"learn":[0.1623001855],"iteration":756,"passed_time":30.52391868,"remaining_time":9.798298863},
{"learn":[0.1622199027],"iteration":757,"passed_time":30.56498532,"remaining_time":9.758214311},
{"learn":[0.1621597099],"iteration":758,"passed_time":30.60447151,"remaining_time":9.717625342},
{"learn":[0.1621498369],"iteration":759,"passed_time":30.64310106,"remaining_time":9.676768756},
{"learn":[0.1620657514],"iteration":760,"passed_time":30.68294434,"remaining_time":9.636299207},
{"learn":[0.1619674581],"iteration":761,"passed_time":30.7235094,"remaining_time":9.59605674},
{"learn":[0.1619576441],"iteration":762,"passed_time":30.76145438,"remaining_time":9.55499959},
{"learn":[0.1617730802],"iteration":763,"passed_time":30.80723808,"remaining_time":9.516371974},
{"learn":[0.1616973025],"iteration":764,"passed_time":30.84756363,"remaining_time":9.476048958},
{"learn":[0.1616427174],"iteration":765,"passed_time":30.88670984,"remaining_time":9.435365669},
{"learn":[0.1616329664],"iteration":766,"passed_time":30.92488232,"remaining_time":9.394390586},
{"learn":[0.1616234347],"iteration":767,"passed_time":30.96230521,"remaining_time":9.353196365},
{"learn":[0.1615043907],"iteration":768,"passed_time":31.0028783,"remaining_time":9.312958242},
{"learn":[0.1614947319],"iteration":769,"passed_time":31.04580564,"remaining_time":9.273422464},
{"learn":[0.1614106636],"iteration":770,"passed_time":31.08426151,"remaining_time":9.232549787},
{"learn":[0.1613463402],"iteration":771,"passed_time":31.12267653,"remaining_time":9.191671307},
{"learn":[0.1612762159],"iteration":772,"passed_time":31.16196019,"remaining_time":9.151054285},
{"learn":[0.1612666035],"iteration":773,"passed_time":31.1987245,"remaining_time":9.109705086},
{"learn":[0.1611263943],"iteration":774,"passed_time":31.24143935,"remaining_time":9.070095296},
{"learn":[0.1611168594],"iteration":775,"passed_time":31.28152446,"remaining_time":9.029718402},
{"learn":[0.1610096715],"iteration":776,"passed_time":31.3240329,"remaining_time":8.990037758},
{"learn":[0.1610003357],"iteration":777,"passed_time":31.36165031,"remaining_time":8.948954201},
{"learn":[0.1609019566],"iteration":778,"passed_time":31.40283766,"remaining_time":8.908892328},
{"learn":[0.1608022226],"iteration":779,"passed_time":31.44269199,"remaining_time":8.868451587},
{"learn":[0.1607928098],"iteration":780,"passed_time":31.48198838,"remaining_time":8.827855898},
{"learn":[0.1607284724],"iteration":781,"passed_time":31.52555843,"remaining_time":8.788454909},
{"learn":[0.1606169593],"iteration":782,"passed_time":31.56495813,"remaining_time":8.747887503},
{"learn":[0.160521925],"iteration":783,"passed_time":31.60489579,"remaining_time":8.707471288},
{"learn":[0.1604295241],"iteration":784,"passed_time":31.64480016,"remaining_time":8.667047178},
{"learn":[0.160370664],"iteration":785,"passed_time":31.68808815,"remaining_time":8.627545628},
{"learn":[0.1603092219],"iteration":786,"passed_time":31.72967142,"remaining_time":8.587573078},
{"learn":[0.1602999299],"iteration":787,"passed_time":31.76807174,"remaining_time":8.546740112},
{"learn":[0.1602906825],"iteration":788,"passed_time":31.80655714,"remaining_time":8.505936067},
{"learn":[0.1601851355],"iteration":789,"passed_time":31.84569775,"remaining_time":8.46531206},
{"learn":[0.1601762021],"iteration":790,"passed_time":31.88219818,"remaining_time":8.42399421},
{"learn":[0.1601119099],"iteration":791,"passed_time":31.92289375,"remaining_time":8.383790278},
{"learn":[0.1599078236],"iteration":792,"passed_time":31.97417416,"remaining_time":8.34634811},
{"learn":[0.1598251101],"iteration":793,"passed_time":32.01266076,"remaining_time":8.305551784},
{"learn":[0.1597511679],"iteration":794,"passed_time":32.05427945,"remaining_time":8.265568915},
{"learn":[0.1596730398],"iteration":795,"passed_time":32.09146168,"remaining_time":8.224444952},
{"learn":[0.1596112588],"iteration":796,"passed_time":32.13089635,"remaining_time":8.18390459},
{"learn":[0.1595678298],"iteration":797,"passed_time":32.17301501,"remaining_time":8.144046407},
{"learn":[0.1594470278],"iteration":798,"passed_time":32.21365069,"remaining_time":8.103809497},
{"learn":[0.1594378427],"iteration":799,"passed_time":32.25217104,"remaining_time":8.063042759},
{"learn":[0.1593157965],"iteration":800,"passed_time":32.29402988,"remaining_time":8.023111043},
{"learn":[0.15923183],"iteration":801,"passed_time":32.33429543,"remaining_time":7.982781165},
{"learn":[0.1592230701],"iteration":802,"passed_time":32.37335716,"remaining_time":7.942156116},
{"learn":[0.1591050231],"iteration":803,"passed_time":32.41364688,"remaining_time":7.901834314},
{"learn":[0.1590307013],"iteration":804,"passed_time":32.45650942,"remaining_time":7.862135822},
{"learn":[0.1589673595],"iteration":805,"passed_time":32.49513453,"remaining_time":7.821409551},
{"learn":[0.1587991238],"iteration":806,"passed_time":32.53539598,"remaining_time":7.781079832},
{"learn":[0.1587234166],"iteration":807,"passed_time":32.5745341,"remaining_time":7.74048335},
{"learn":[0.1585925153],"iteration":808,"passed_time":32.61234961,"remaining_time":7.699578214},
{"learn":[0.1585076014],"iteration":809,"passed_time":32.65493972,"remaining_time":7.659800674},
{"learn":[0.1584984156],"iteration":810,"passed_time":32.69737127,"remaining_time":7.619979248},
{"learn":[0.1584168218],"iteration":811,"passed_time":32.73631515,"remaining_time":7.579343903},
{"learn":[0.1584077574],"iteration":812,"passed_time":32.77514185,"remaining_time":7.538685763},
{"learn":[0.1583261992],"iteration":813,"passed_time":32.81370324,"remaining_time":7.497971502},
{"learn":[0.1582646592],"iteration":814,"passed_time":32.85377639,"remaining_time":7.457605685},
{"learn":[0.1581781521],"iteration":815,"passed_time":32.89844977,"remaining_time":7.418277889},
{"learn":[0.1580456009],"iteration":816,"passed_time":32.94002277,"remaining_time":7.378242554},
{"learn":[0.1579517021],"iteration":817,"passed_time":32.98004869,"remaining_time":7.337859244},
{"learn":[0.1578482253],"iteration":818,"passed_time":33.01943812,"remaining_time":7.297336142},
{"learn":[0.1577226276],"iteration":819,"passed_time":33.0589963,"remaining_time":7.256852846},
{"learn":[0.1576081492],"iteration":820,"passed_time":33.10191862,"remaining_time":7.217105277},
{"learn":[0.1575468489],"iteration":821,"passed_time":33.14185421,"remaining_time":7.176703224},
{"learn":[0.1575377223],"iteration":822,"passed_time":33.18236318,"remaining_time":7.136425616},
{"learn":[0.1574700044],"iteration":823,"passed_time":33.22161246,"remaining_time":7.095878389},
{"learn":[0.1573815352],"iteration":824,"passed_time":33.26011126,"remaining_time":7.055175115},
{"learn":[0.1572693094],"iteration":825,"passed_time":33.30187827,"remaining_time":7.015165641},
{"learn":[0.1572603448],"iteration":826,"passed_time":33.33889093,"remaining_time":6.974157352},
{"learn":[0.1571755301],"iteration":827,"passed_time":33.37752103,"remaining_time":6.933494707},
{"learn":[0.1571352698],"iteration":828,"passed_time":33.41774697,"remaining_time":6.893166142},
{"learn":[0.1570211493],"iteration":829,"passed_time":33.4596149,"remaining_time":6.853174137},
{"learn":[0.1569495761],"iteration":830,"passed_time":33.50003274,"remaining_time":6.812882712},
{"learn":[0.1567754695],"iteration":831,"passed_time":33.53971316,"remaining_time":6.77244208},
{"learn":[0.1567202861],"iteration":832,"passed_time":33.57932719,"remaining_time":6.731989965},
{"learn":[0.1566555716],"iteration":833,"passed_time":33.61914707,"remaining_time":6.691580832},
{"learn":[0.1565788085],"iteration":834,"passed_time":33.66289161,"remaining_time":6.651948641},
{"learn":[0.1564175479],"iteration":835,"passed_time":33.70579459,"remaining_time":6.612141523},
{"learn":[0.15632912],"iteration":836,"passed_time":33.74347467,"remaining_time":6.571309883},
{"learn":[0.1562512239],"iteration":837,"passed_time":33.7842343,"remaining_time":6.531081094},
{"learn":[0.1561385167],"iteration":838,"passed_time":33.8226904,"remaining_time":6.490409004},
{"learn":[0.156129652],"iteration":839,"passed_time":33.8639339,"remaining_time":6.450273123},
{"learn":[0.1560739384],"iteration":840,"passed_time":33.90451427,"remaining_time":6.410009237},
{"learn":[0.1559983037],"iteration":841,"passed_time":33.94192083,"remaining_time":6.36914904},
{"learn":[0.1559309533],"iteration":842,"passed_time":33.98033929,"remaining_time":6.32848549},
{"learn":[0.1558485025],"iteration":843,"passed_time":34.01852459,"remaining_time":6.287784167},
{"learn":[0.1557502143],"iteration":844,"passed_time":34.05734263,"remaining_time":6.247204861},
{"learn":[0.1556547642],"iteration":845,"passed_time":34.09795076,"remaining_time":6.206955576},
{"learn":[0.1555614109],"iteration":846,"passed_time":34.13778516,"remaining_time":6.166565678},
{"learn":[0.1554465097],"iteration":847,"passed_time":34.1784932,"remaining_time":6.126333686},
{"learn":[0.155437589],"iteration":848,"passed_time":34.21415444,"remaining_time":6.085202969},
{"learn":[0.1553342082],"iteration":849,"passed_time":34.25423347,"remaining_time":6.044864731},
{"learn":[0.1553160464],"iteration":850,"passed_time":34.29487174,"remaining_time":6.004625017},
{"learn":[0.1553072332],"iteration":851,"passed_time":34.33323738,"remaining_time":5.963989592},
{"learn":[0.1552047532],"iteration":852,"passed_time":34.3776259,"remaining_time":5.924397429},
{"learn":[0.1550608292],"iteration":853,"passed_time":34.41899493,"remaining_time":5.884277821},
{"learn":[0.1550520452],"iteration":854,"passed_time":34.45705327,"remaining_time":5.843593829},
{"learn":[0.1549999167],"iteration":855,"passed_time":34.49543081,"remaining_time":5.80296967},
{"learn":[0.1549912542],"iteration":856,"passed_time":34.53287438,"remaining_time":5.762194908},
{"learn":[0.1548939298],"iteration":857,"passed_time":34.57356325,"remaining_time":5.721965013},
{"learn":[0.1548853677],"iteration":858,"passed_time":34.61407418,"remaining_time":5.681704842},
{"learn":[0.1547873643],"iteration":859,"passed_time":34.65325004,"remaining_time":5.64122675},
{"learn":[0.1546945101],"iteration":860,"passed_time":34.693561,"remaining_time":5.600934935},
{"learn":[0.1546414973],"iteration":861,"passed_time":34.73000305,"remaining_time":5.56002369},
{"learn":[0.1546330032],"iteration":862,"passed_time":34.7677829,"remaining_time":5.519335176},
{"learn":[0.1545396442],"iteration":863,"passed_time":34.8066496,"remaining_time":5.478824474},
{"learn":[0.1544619331],"iteration":864,"passed_time":34.84929324,"remaining_time":5.438907037},
{"learn":[0.1543651218],"iteration":865,"passed_time":34.88678195,"remaining_time":5.398185659},
{"learn":[0.1542627811],"iteration":866,"passed_time":34.92475118,"remaining_time":5.357545453},
{"learn":[0.1541770401],"iteration":867,"passed_time":34.96244465,"remaining_time":5.316869464},
{"learn":[0.1540867691],"iteration":868,"passed_time":35.00048083,"remaining_time":5.276252001},
{"learn":[0.1540369568],"iteration":869,"passed_time":35.04037332,"remaining_time":5.235917852},
{"learn":[0.1540284945],"iteration":870,"passed_time":35.07807817,"remaining_time":5.195260716},
{"learn":[0.153929032],"iteration":871,"passed_time":35.11847181,"remaining_time":5.155005037},
{"learn":[0.1538010654],"iteration":872,"passed_time":35.15814992,"remaining_time":5.114644948},
{"learn":[0.1537924302],"iteration":873,"passed_time":35.19455203,"remaining_time":5.073814138},
{"learn":[0.1537510211],"iteration":874,"passed_time":35.23360161,"remaining_time":5.033371659},
{"learn":[0.1536695321],"iteration":875,"passed_time":35.27389655,"remaining_time":4.993108643},
{"learn":[0.1535770067],"iteration":876,"passed_time":35.31552321,"remaining_time":4.953032331},
{"learn":[0.1535680364],"iteration":877,"passed_time":35.35555536,"remaining_time":4.912730927},
{"learn":[0.1534616744],"iteration":878,"passed_time":35.39384125,"remaining_time":4.872189751},
{"learn":[0.1534535917],"iteration":879,"passed_time":35.43232745,"remaining_time":4.831681016},
{"learn":[0.1533675677],"iteration":880,"passed_time":35.4701883,"remaining_time":4.791092404},
{"learn":[0.1533388634],"iteration":881,"passed_time":35.52167461,"remaining_time":4.752332884},
{"learn":[0.1532099279],"iteration":882,"passed_time":35.56415051,"remaining_time":4.712350634},
{"learn":[0.1531394628],"iteration":883,"passed_time":35.60227569,"remaining_time":4.671791832},
{"learn":[0.1530417868],"iteration":884,"passed_time":35.64112353,"remaining_time":4.631332436},
{"learn":[0.1529662603],"iteration":885,"passed_time":35.67818154,"remaining_time":4.590646384},
{"learn":[0.1528891665],"iteration":886,"passed_time":35.71867676,"remaining_time":4.550406397},
{"learn":[0.1528080228],"iteration":887,"passed_time":35.75924505,"remaining_time":4.510175052},
{"learn":[0.1527023703],"iteration":888,"passed_time":35.80216615,"remaining_time":4.470236718},
{"learn":[0.1526940149],"iteration":889,"passed_time":35.84261567,"remaining_time":4.429986207},
{"learn":[0.1526204453],"iteration":890,"passed_time":35.8813879,"remaining_time":4.389530057},
{"learn":[0.1524878693],"iteration":891,"passed_time":35.92152249,"remaining_time":4.349242634},
{"learn":[0.1524796416],"iteration":892,"passed_time":35.95983191,"remaining_time":4.308736858},
{"learn":[0.1523891424],"iteration":893,"passed_time":36.0001024,"remaining_time":4.268468518},
{"learn":[0.1522000783],"iteration":894,"passed_time":36.04460882,"remaining_time":4.228697124},
{"learn":[0.1521357123],"iteration":895,"passed_time":36.08164296,"remaining_time":4.188047844},
{"learn":[0.1520431054],"iteration":896,"passed_time":36.1196121,"remaining_time":4.147513986},
{"learn":[0.1520351976],"iteration":897,"passed_time":36.15779429,"remaining_time":4.107010042},
{"learn":[0.1519489625],"iteration":898,"passed_time":36.19811076,"remaining_time":4.066751041},
{"learn":[0.1518335762],"iteration":899,"passed_time":36.24222109,"remaining_time":4.026913455},
{"learn":[0.1517704557],"iteration":900,"passed_time":36.28095464,"remaining_time":3.986475593},
{"learn":[0.1517623056],"iteration":901,"passed_time":36.32023353,"remaining_time":3.946100761},
{"learn":[0.1517344297],"iteration":902,"passed_time":36.35919821,"remaining_time":3.905694603},
{"learn":[0.1516802355],"iteration":903,"passed_time":36.39666836,"remaining_time":3.865132923},
{"learn":[0.1515777429],"iteration":904,"passed_time":36.43815891,"remaining_time":3.825000107},
{"learn":[0.1515696379],"iteration":905,"passed_time":36.47596278,"remaining_time":3.78448179},
{"learn":[0.1515616004],"iteration":906,"passed_time":36.51538947,"remaining_time":3.744135855},
{"learn":[0.1515070235],"iteration":907,"passed_time":36.55553708,"remaining_time":3.703864991},
{"learn":[0.1514245338],"iteration":908,"passed_time":36.59297646,"remaining_time":3.663323276},
{"learn":[0.1513813108],"iteration":909,"passed_time":36.63198932,"remaining_time":3.622943999},
{"learn":[0.1513145714],"iteration":910,"passed_time":36.67054166,"remaining_time":3.582522731},
{"learn":[0.1512012755],"iteration":911,"passed_time":36.71313423,"remaining_time":3.542495408},
{"learn":[0.1511386935],"iteration":912,"passed_time":36.7549885,"remaining_time":3.502392114},
{"learn":[0.151075503],"iteration":913,"passed_time":36.79412003,"remaining_time":3.462028799},
{"learn":[0.1510177695],"iteration":914,"passed_time":36.83269198,"remaining_time":3.421616195},
{"learn":[0.1509565334],"iteration":915,"passed_time":36.87107214,"remaining_time":3.381190021},
{"learn":[0.1508681087],"iteration":916,"passed_time":36.91106208,"remaining_time":3.340914016},
{"learn":[0.1507727623],"iteration":917,"passed_time":36.95492333,"remaining_time":3.300984437},
{"learn":[0.1507647343],"iteration":918,"passed_time":36.9925878,"remaining_time":3.260500121},
{"learn":[0.1507133312],"iteration":919,"passed_time":37.03095676,"remaining_time":3.220083197},
{"learn":[0.1507053858],"iteration":920,"passed_time":37.06830716,"remaining_time":3.17958335},
{"learn":[0.1506075039],"iteration":921,"passed_time":37.10933599,"remaining_time":3.139401527},
{"learn":[0.1505344086],"iteration":922,"passed_time":37.15087609,"remaining_time":3.099260519},
{"learn":[0.1505265458],"iteration":923,"passed_time":37.18981383,"remaining_time":3.058902436},
{"learn":[0.150384627],"iteration":924,"passed_time":37.22990727,"remaining_time":3.01864113},
{"learn":[0.1503770301],"iteration":925,"passed_time":37.26656994,"remaining_time":2.978106021},
{"learn":[0.1502735831],"iteration":926,"passed_time":37.30716625,"remaining_time":2.937889036},
{"learn":[0.1502268422],"iteration":927,"passed_time":37.34501186,"remaining_time":2.897457817},
{"learn":[0.1501407897],"iteration":928,"passed_time":37.38668463,"remaining_time":2.85732466},
{"learn":[0.1499991856],"iteration":929,"passed_time":37.42939348,"remaining_time":2.817266176},
{"learn":[0.1499493389],"iteration":930,"passed_time":37.4688648,"remaining_time":2.776962053},
{"learn":[0.149876641],"iteration":931,"passed_time":37.50781778,"remaining_time":2.736621898},
{"learn":[0.1498687623],"iteration":932,"passed_time":37.5444315,"remaining_time":2.696116731},
{"learn":[0.1497962259],"iteration":933,"passed_time":37.58430196,"remaining_time":2.655850032},
{"learn":[0.1497487501],"iteration":934,"passed_time":37.62689832,"remaining_time":2.61577368},
{"learn":[0.1496823839],"iteration":935,"passed_time":37.66876145,"remaining_time":2.575641809},
{"learn":[0.1496015167],"iteration":936,"passed_time":37.70971782,"remaining_time":2.535445275},
{"learn":[0.1495169659],"iteration":937,"passed_time":37.74943531,"remaining_time":2.495165234},
{"learn":[0.149459252],"iteration":938,"passed_time":37.78875085,"remaining_time":2.454860279},
{"learn":[0.1493202279],"iteration":939,"passed_time":37.83081943,"remaining_time":2.414733155},
{"learn":[0.1493125114],"iteration":940,"passed_time":37.86950944,"remaining_time":2.374390071},
{"learn":[0.1492211062],"iteration":941,"passed_time":37.91274131,"remaining_time":2.334330144},
{"learn":[0.1492134431],"iteration":942,"passed_time":37.95203154,"remaining_time":2.294025236},
{"learn":[0.1490935828],"iteration":943,"passed_time":37.99109024,"remaining_time":2.253708743},
{"learn":[0.1490859343],"iteration":944,"passed_time":38.02891911,"remaining_time":2.213323334},
{"learn":[0.1489936104],"iteration":945,"passed_time":38.06704811,"remaining_time":2.172960463},
{"learn":[0.1488707294],"iteration":946,"passed_time":38.10925613,"remaining_time":2.132830596},
{"learn":[0.1487881622],"iteration":947,"passed_time":38.15237382,"remaining_time":2.092746243},
{"learn":[0.1487012202],"iteration":948,"passed_time":38.19005057,"remaining_time":2.052363097},
{"learn":[0.1485951729],"iteration":949,"passed_time":38.22878806,"remaining_time":2.012041477},
{"learn":[0.1485875994],"iteration":950,"passed_time":38.26605074,"remaining_time":1.971647199},
{"learn":[0.148521656],"iteration":951,"passed_time":38.30593813,"remaining_time":1.931391839},
{"learn":[0.1484741147],"iteration":952,"passed_time":38.34874449,"remaining_time":1.891281208},
{"learn":[0.148409249],"iteration":953,"passed_time":38.38856512,"remaining_time":1.85102096},
{"learn":[0.1483225549],"iteration":954,"passed_time":38.42806974,"remaining_time":1.810746741},
{"learn":[0.1482478015],"iteration":955,"passed_time":38.46707106,"remaining_time":1.770450969},
{"learn":[0.1481897259],"iteration":956,"passed_time":38.50698594,"remaining_time":1.73019895},
{"learn":[0.1481111984],"iteration":957,"passed_time":38.54679504,"remaining_time":1.689942998},
{"learn":[0.1480295448],"iteration":958,"passed_time":38.58463889,"remaining_time":1.649603957},
{"learn":[0.1477853285],"iteration":959,"passed_time":38.62915733,"remaining_time":1.609548222},
{"learn":[0.1477776012],"iteration":960,"passed_time":38.66619191,"remaining_time":1.569179484},
{"learn":[0.1477118174],"iteration":961,"passed_time":38.70870817,"remaining_time":1.52903421},
{"learn":[0.1476508452],"iteration":962,"passed_time":38.74721086,"remaining_time":1.488729805},
{"learn":[0.1475951182],"iteration":963,"passed_time":38.78675015,"remaining_time":1.448467848},
{"learn":[0.1475874704],"iteration":964,"passed_time":38.82832943,"remaining_time":1.408281378},
{"learn":[0.1475379181],"iteration":965,"passed_time":38.86895477,"remaining_time":1.368058449},
{"learn":[0.1474246782],"iteration":966,"passed_time":38.90978858,"remaining_time":1.327841803},
{"learn":[0.1474171842],"iteration":967,"passed_time":38.94829444,"remaining_time":1.287546924},
{"learn":[0.1473696855],"iteration":968,"passed_time":38.98625018,"remaining_time":1.247238138},
{"learn":[0.1472816989],"iteration":969,"passed_time":39.02502291,"remaining_time":1.206959471},
{"learn":[0.1472741776],"iteration":970,"passed_time":39.06417142,"remaining_time":1.16669513},
{"learn":[0.1471865508],"iteration":971,"passed_time":39.10625549,"remaining_time":1.126517648},
{"learn":[0.1471121788],"iteration":972,"passed_time":39.14575517,"remaining_time":1.086264532},
{"learn":[0.1470426973],"iteration":973,"passed_time":39.18338212,"remaining_time":1.045962972},
{"learn":[0.146988006],"iteration":974,"passed_time":39.22304172,"remaining_time":1.005719019},
{"learn":[0.1468689594],"iteration":975,"passed_time":39.26196848,"remaining_time":0.9654582412},
{"learn":[0.1468616746],"iteration":976,"passed_time":39.30421061,"remaining_time":0.9252782437},
{"learn":[0.1468007253],"iteration":977,"passed_time":39.345121,"remaining_time":0.8850640715},
{"learn":[0.1467474035],"iteration":978,"passed_time":39.39263027,"remaining_time":0.8449900262},
{"learn":[0.1466707217],"iteration":979,"passed_time":39.43249553,"remaining_time":0.8047448068},
{"learn":[0.1465858841],"iteration":980,"passed_time":39.47260732,"remaining_time":0.7645051366},
{"learn":[0.146507335],"iteration":981,"passed_time":39.51088875,"remaining_time":0.7242321767},
{"learn":[0.146499946],"iteration":982,"passed_time":39.55272995,"remaining_time":0.6840248313},
{"learn":[0.1464707616],"iteration":983,"passed_time":39.59403926,"remaining_time":0.6438055164},
{"learn":[0.1463915958],"iteration":984,"passed_time":39.63463846,"remaining_time":0.6035731745},
{"learn":[0.1463380413],"iteration":985,"passed_time":39.6733052,"remaining_time":0.56331265},
{"learn":[0.1462614772],"iteration":986,"passed_time":39.71303975,"remaining_time":0.5230694191},
{"learn":[0.1462156531],"iteration":987,"passed_time":39.75259285,"remaining_time":0.4828250143},
{"learn":[0.1462084052],"iteration":988,"passed_time":39.79262841,"remaining_time":0.4425873737},
{"learn":[0.1461125437],"iteration":989,"passed_time":39.83626906,"remaining_time":0.4023865562},
{"learn":[0.1460878499],"iteration":990,"passed_time":39.87415333,"remaining_time":0.3621265186},
{"learn":[0.1460405687],"iteration":991,"passed_time":39.91137082,"remaining_time":0.3218658937},
{"learn":[0.1459664466],"iteration":992,"passed_time":39.95217059,"remaining_time":0.2816366507},
{"learn":[0.1459591268],"iteration":993,"passed_time":39.99243726,"remaining_time":0.2414030418},
{"learn":[0.1458390592],"iteration":994,"passed_time":40.03573465,"remaining_time":0.2011845962},
{"learn":[0.145831817],"iteration":995,"passed_time":40.07467888,"remaining_time":0.1609424855},
{"learn":[0.145758124],"iteration":996,"passed_time":40.11287835,"remaining_time":0.1207007372},
{"learn":[0.1457362715],"iteration":997,"passed_time":40.15193394,"remaining_time":0.08046479747},
{"learn":[0.1456163108],"iteration":998,"passed_time":40.19262415,"remaining_time":0.04023285701},
{"learn":[0.1456041851],"iteration":999,"passed_time":40.23521718,"remaining_time":0}
]}